Workbook

Sheet 销售物业-海沧A璞盛
A1: 一、工程进度： | C1: =+[1]关键节点!G2 -> 竣备 | D1: =+[1]关键节点!H2 -> 交付/开业 | E1: =+[1]关键节点!I2 -> 交付 （合同约定）
C2: =+[1]关键节点!G8 -> 46265 | D2: =+[1]关键节点!H8 -> 住宅：2027/4/30 商业：2027/5/1 | E2: =+[1]关键节点!I8 -> 46568
A3: 二、销售情况 | P3: W | S3: X | V3: Y | Y3: Z | AB3: AA | AE3: AB
A4: 海沧璞盛 | D4: 合计 | G4: 2025年及以前已实现 | J4: 2026年1-3月 | M4: 截止26年3月待售 | P4: 2026年预计 | S4: 2027年预计 | V4: 2028年预计 | Y4: 2029年预计 | AB4: 2030年预计 | AE4: 2031年及以后预计
D5: 合计 | E5: 一期 | F5: 二期 | G5: 合计 | H5: 一期 | I5: 二期 | P5: 合计 | Q5: 一期 | R5: 二期 | S5: 合计 | T5: 一期 | U5: 二期 | V5: 合计 | W5: 一期 | X5: 二期 | Y5: 合计 | Z5: 一期 | AA5: 二期 | AB5: 合计 | AC5: 一期 | AD5: 二期 | AE5: 合计 | AF5: 一期 | AG5: 二期
A6: 签约 | C6: 合计 | D6: =SUM(D8:D11) -> 42.089468 | E6: =SUM(E8:E11) -> 33.553411 | F6: =SUM(F8:F11) -> 8.5360571 | G6: =SUM(G8:G11) -> 29.534337 | H6: =SUM(H8:H11) -> 22.108743 | I6: =SUM(I8:I11) -> 7.4255942 | J6: =SUM(J8:J11) -> 0 | K6: =SUM(K8:K11) -> 0 | ... AG6: =SUM(AG8:AG11) -> 0
C7: 住宅 | D7: =SUM(D8:D9) -> 39.628221 | E7: =SUM(E8:E9) -> 31.431942 | F7: =SUM(F8:F9) -> 8.196279 | G7: =SUM(G8:G9) -> 29.250237 | H7: =SUM(H8:H9) -> 21.892443 | I7: =SUM(I8:I9) -> 7.3577942 | P7: =SUM(P8:P9) -> 6.6912545 | Q7: =SUM(Q8:Q9) -> 5.8527696 | R7: =SUM(R8:R9) -> 0.83848488 | S7: =SUM(S8:S9) -> 3.6867291 | T7: =SUM(T8:T9) -> 3.6867291 | U7: =SUM(U8:U9) -> 0 | V7: =SUM(V8:V9) -> 0 | W7: =SUM(W8:W9) -> 0 | ... AG7: =SUM(AG8:AG9) -> 0
C8: 其中：普宅 | D8: =SUM(E8:F8) -> 30.637492 | E8: =SUM(H8,Q8,T8,W8,Z8,AC8,AF8) -> 22.441213 | F8: =SUM(I8,R8,U8,X8,AA8,AD8,AG8) -> 8.196279 | G8: =SUM(H8:I8) -> 29.250237 | H8: =(SUMIFS('[2]1.1地产销售计划表'!N:N,'[2]1.1地产销售计划表'!B:B,"海沧中心璞盛项目（一期）",'[2]1.1地产销售计划表'!G:G,"住宅-精装普宅",'[2]1.1地产销售计划表'!H:H,"签约(元）")+SUMIFS('[2]1.1地产销售计划表'!V:V,'[2]1.1地产销售计划表'!B:B,"海沧中心璞盛项目（一期）",'[2]1.1地产销售计划表'!G:G,"住宅-精装普宅",'[2]1.1地产销售计划表'!H:H,"签约(元）"))/100000000 -> 21.892443 | I8: =(SUMIFS('[2]1.1地产销售计划表'!N:N,'[2]1.1地产销售计划表'!B:B,"海沧中心璞盛项目（二期）",'[2]1.1地产销售计划表'!G:G,"住宅-精装普宅",'[2]1.1地产销售计划表'!H:H,"签约(元）")+SUMIFS('[2]1.1地产销售计划表'!V:V,'[2]1.1地产销售计划表'!B:B,"海沧中心璞盛项目（二期）",'[2]1.1地产销售计划表'!G:G,"住宅-精装普宅",'[2]1.1地产销售计划表'!H:H,"签约(元）"))/100000000 -> 7.3577942 | P8: =SUM(Q8:R8) -> 1.3872545 | Q8: =SUMIFS('[2]1.1地产销售计划表'!W:W,'[2]1.1地产销售计划表'!B:B,"海沧中心璞盛项目（一期）",'[2]1.1地产销售计划表'!G:G,"住宅-精装普宅",'[2]1.1地产销售计划表'!H:H,"签约(元）")/100000000 -> 0.54876958 | R8: =SUMIFS('[2]1.1地产销售计划表'!W:W,'[2]1.1地产销售计划表'!B:B,"海沧中心璞盛项目（二期）",'[2]1.1地产销售计划表'!G:G,"住宅-精装普宅",'[2]1.1地产销售计划表'!H:H,"签约(元）")/100000000 -> 0.83848488 | S8: =SUM(T8:U8) -> 0 | T8: =SUMIFS('[2]1.1地产销售计划表'!X:X,'[2]1.1地产销售计划表'!B:B,"海沧中心璞盛项目（一期）",'[2]1.1地产销售计划表'!G:G,"住宅-精装普宅",'[2]1.1地产销售计划表'!H:H,"签约(元）")/100000000 -> 0 | U8: =SUMIFS('[2]1.1地产销售计划表'!X:X,'[2]1.1地产销售计划表'!B:B,"海沧中心璞盛项目（二期）",'[2]1.1地产销售计划表'!G:G,"住宅-精装普宅",'[2]1.1地产销售计划表'!H:H,"签约(元）")/100000000 -> 0 | V8: =SUM(W8:X8) -> 0 | W8: =SUMIFS('[2]1.1地产销售计划表'!Y:Y,'[2]1.1地产销售计划表'!B:B,"海沧中心璞盛项目（一期）",'[2]1.1地产销售计划表'!G:G,"住宅-精装普宅",'[2]1.1地产销售计划表'!H:H,"签约(元）")/100000000 -> 0 | X8: =SUMIFS('[2]1.1地产销售计划表'!Y:Y,'[2]1.1地产销售计划表'!B:B,"海沧中心璞盛项目（二期）",'[2]1.1地产销售计划表'!G:G,"住宅-精装普宅",'[2]1.1地产销售计划表'!H:H,"签约(元）")/100000000 -> 0 | Y8: =SUM(Z8:AA8) -> 0 | Z8: =SUMIFS('[2]1.1地产销售计划表'!Z:Z,'[2]1.1地产销售计划表'!B:B,"海沧中心璞盛项目（一期）",'[2]1.1地产销售计划表'!G:G,"住宅-精装普宅",'[2]1.1地产销售计划表'!H:H,"签约(元）")/100000000 -> 0 | AA8: =SUMIFS('[2]1.1地产销售计划表'!Z:Z,'[2]1.1地产销售计划表'!B:B,"海沧中心璞盛项目（二期）",'[2]1.1地产销售计划表'!G:G,"住宅-精装普宅",'[2]1.1地产销售计划表'!H:H,"签约(元）")/100000000 -> 0 | AB8: =SUM(AC8:AD8) -> 0 | AC8: =SUMIFS('[2]1.1地产销售计划表'!AA:AA,'[2]1.1地产销售计划表'!B:B,"海沧中心璞盛项目（一期）",'[2]1.1地产销售计划表'!G:G,"住宅-精装普宅",'[2]1.1地产销售计划表'!H:H,"签约(元）")/100000000 -> 0 | AD8: =SUMIFS('[2]1.1地产销售计划表'!AA:AA,'[2]1.1地产销售计划表'!B:B,"海沧中心璞盛项目（二期）",'[2]1.1地产销售计划表'!G:G,"住宅-精装普宅",'[2]1.1地产销售计划表'!H:H,"签约(元）")/100000000 -> 0 | AE8: =SUM(AF8:AG8) -> 0 | AF8: =SUMIFS('[2]1.1地产销售计划表'!AB:AB,'[2]1.1地产销售计划表'!B:B,"海沧中心璞盛项目（一期）",'[2]1.1地产销售计划表'!G:G,"住宅-精装普宅",'[2]1.1地产销售计划表'!H:H,"签约(元）")/100000000 -> 0 | AG8: =SUMIFS('[2]1.1地产销售计划表'!AB:AB,'[2]1.1地产销售计划表'!B:B,"海沧中心璞盛项目（二期）",'[2]1.1地产销售计划表'!G:G,"住宅-精装普宅",'[2]1.1地产销售计划表'!H:H,"签约(元）")/100000000 -> 0
C9: 非普宅 | D9: =SUM(E9:F9) -> 8.9907291 | E9: =SUM(H9,Q9,T9,W9,Z9,AC9,AF9) -> 8.9907291 | F9: =SUM(I9,R9,U9,X9,AA9,AD9,AG9) -> 0 | G9: =SUM(H9:I9) -> 0 | H9: =(SUMIFS('[2]1.1地产销售计划表'!N:N,'[2]1.1地产销售计划表'!B:B,"海沧中心璞盛项目（一期）",'[2]1.1地产销售计划表'!G:G,"住宅-精装非普宅",'[2]1.1地产销售计划表'!H:H,"签约(元）")+SUMIFS('[2]1.1地产销售计划表'!V:V,'[2]1.1地产销售计划表'!B:B,"海沧中心璞盛项目（一期）",'[2]1.1地产销售计划表'!G:G,"住宅-精装非普宅",'[2]1.1地产销售计划表'!H:H,"签约(元）"))/100000000 -> 0 | I9: =(SUMIFS('[2]1.1地产销售计划表'!N:N,'[2]1.1地产销售计划表'!B:B,"海沧中心璞盛项目（二期）",'[2]1.1地产销售计划表'!G:G,"住宅-精装非普宅",'[2]1.1地产销售计划表'!H:H,"签约(元）")+SUMIFS('[2]1.1地产销售计划表'!V:V,'[2]1.1地产销售计划表'!B:B,"海沧中心璞盛项目（二期）",'[2]1.1地产销售计划表'!G:G,"住宅-精装非普宅",'[2]1.1地产销售计划表'!H:H,"签约(元）"))/100000000 -> 0 | P9: =SUM(Q9:R9) -> 5.304 | Q9: =SUMIFS('[2]1.1地产销售计划表'!W:W,'[2]1.1地产销售计划表'!B:B,"海沧中心璞盛项目（一期）",'[2]1.1地产销售计划表'!G:G,"住宅-精装非普宅",'[2]1.1地产销售计划表'!H:H,"签约(元）")/100000000 -> 5.304 | R9: =SUMIFS('[2]1.1地产销售计划表'!W:W,'[2]1.1地产销售计划表'!B:B,"海沧中心璞盛项目（二期）",'[2]1.1地产销售计划表'!G:G,"住宅-精装非普宅",'[2]1.1地产销售计划表'!H:H,"签约(元）")/100000000 -> 0 | S9: =SUM(T9:U9) -> 3.6867291 | T9: =SUMIFS('[2]1.1地产销售计划表'!X:X,'[2]1.1地产销售计划表'!B:B,"海沧中心璞盛项目（一期）",'[2]1.1地产销售计划表'!G:G,"住宅-精装非普宅",'[2]1.1地产销售计划表'!H:H,"签约(元）")/100000000 -> 3.6867291 | U9: =SUMIFS('[2]1.1地产销售计划表'!X:X,'[2]1.1地产销售计划表'!B:B,"海沧中心璞盛项目（二期）",'[2]1.1地产销售计划表'!G:G,"住宅-精装非普宅",'[2]1.1地产销售计划表'!H:H,"签约(元）")/100000000 -> 0 | V9: =SUM(W9:X9) -> 0 | W9: =SUMIFS('[2]1.1地产销售计划表'!Y:Y,'[2]1.1地产销售计划表'!B:B,"海沧中心璞盛项目（一期）",'[2]1.1地产销售计划表'!G:G,"住宅-精装非普宅",'[2]1.1地产销售计划表'!H:H,"签约(元）")/100000000 -> 0 | X9: =SUMIFS('[2]1.1地产销售计划表'!Y:Y,'[2]1.1地产销售计划表'!B:B,"海沧中心璞盛项目（二期）",'[2]1.1地产销售计划表'!G:G,"住宅-精装非普宅",'[2]1.1地产销售计划表'!H:H,"签约(元）")/100000000 -> 0 | Y9: =SUM(Z9:AA9) -> 0 | Z9: =SUMIFS('[2]1.1地产销售计划表'!Z:Z,'[2]1.1地产销售计划表'!B:B,"海沧中心璞盛项目（一期）",'[2]1.1地产销售计划表'!G:G,"住宅-精装非普宅",'[2]1.1地产销售计划表'!H:H,"签约(元）")/100000000 -> 0 | AA9: =SUMIFS('[2]1.1地产销售计划表'!Z:Z,'[2]1.1地产销售计划表'!B:B,"海沧中心璞盛项目（二期）",'[2]1.1地产销售计划表'!G:G,"住宅-精装非普宅",'[2]1.1地产销售计划表'!H:H,"签约(元）")/100000000 -> 0 | AB9: =SUM(AC9:AD9) -> 0 | AC9: =SUMIFS('[2]1.1地产销售计划表'!AA:AA,'[2]1.1地产销售计划表'!B:B,"海沧中心璞盛项目（一期）",'[2]1.1地产销售计划表'!G:G,"住宅-精装非普宅",'[2]1.1地产销售计划表'!H:H,"签约(元）")/100000000 -> 0 | AD9: =SUMIFS('[2]1.1地产销售计划表'!AA:AA,'[2]1.1地产销售计划表'!B:B,"海沧中心璞盛项目（二期）",'[2]1.1地产销售计划表'!G:G,"住宅-精装非普宅",'[2]1.1地产销售计划表'!H:H,"签约(元）")/100000000 -> 0 | AE9: =SUM(AF9:AG9) -> 0 | AF9: =SUMIFS('[2]1.1地产销售计划表'!AB:AB,'[2]1.1地产销售计划表'!B:B,"海沧中心璞盛项目（一期）",'[2]1.1地产销售计划表'!G:G,"住宅-精装非普宅",'[2]1.1地产销售计划表'!H:H,"签约(元）")/100000000 -> 0 | AG9: =SUMIFS('[2]1.1地产销售计划表'!AB:AB,'[2]1.1地产销售计划表'!B:B,"海沧中心璞盛项目（二期）",'[2]1.1地产销售计划表'!G:G,"住宅-精装非普宅",'[2]1.1地产销售计划表'!H:H,"签约(元）")/100000000 -> 0
C10: 商业 | D10: =SUM(E10:F10) -> 0.710247 | E10: =SUM(H10,Q10,T10,W10,Z10,AC10,AF10) -> 0.628269 | F10: =SUM(I10,R10,U10,X10,AA10,AD10,AG10) -> 0.081978 | G10: =SUM(H10:I10) -> 0 | H10: =(SUMIFS('[2]1.1地产销售计划表'!N:N,'[2]1.1地产销售计划表'!B:B,"海沧中心璞盛项目（一期）",'[2]1.1地产销售计划表'!G:G,"商业",'[2]1.1地产销售计划表'!H:H,"签约(元）")+SUMIFS('[2]1.1地产销售计划表'!V:V,'[2]1.1地产销售计划表'!B:B,"海沧中心璞盛项目（一期）",'[2]1.1地产销售计划表'!G:G,"商业",'[2]1.1地产销售计划表'!H:H,"签约(元）"))/100000000 -> 0 | I10: =(SUMIFS('[2]1.1地产销售计划表'!N:N,'[2]1.1地产销售计划表'!B:B,"海沧中心璞盛项目（二期）",'[2]1.1地产销售计划表'!G:G,"商业",'[2]1.1地产销售计划表'!H:H,"签约(元）")+SUMIFS('[2]1.1地产销售计划表'!V:V,'[2]1.1地产销售计划表'!B:B,"海沧中心璞盛项目（二期）",'[2]1.1地产销售计划表'!G:G,"商业",'[2]1.1地产销售计划表'!H:H,"签约(元）"))/100000000 -> 0 | P10: =SUM(Q10:R10) -> 0 | Q10: =SUMIFS('[2]1.1地产销售计划表'!W:W,'[2]1.1地产销售计划表'!B:B,"海沧中心璞盛项目（一期）",'[2]1.1地产销售计划表'!G:G,"商业",'[2]1.1地产销售计划表'!H:H,"签约(元）")/100000000 -> 0 | R10: =SUMIFS('[2]1.1地产销售计划表'!W:W,'[2]1.1地产销售计划表'!B:B,"海沧中心璞盛项目（二期）",'[2]1.1地产销售计划表'!G:G,"商业",'[2]1.1地产销售计划表'!H:H,"签约(元）")/100000000 -> 0 | S10: =SUM(T10:U10) -> 0 | T10: =SUMIFS('[2]1.1地产销售计划表'!X:X,'[2]1.1地产销售计划表'!B:B,"海沧中心璞盛项目（一期）",'[2]1.1地产销售计划表'!G:G,"商业",'[2]1.1地产销售计划表'!H:H,"签约(元）")/100000000 -> 0 | U10: =SUMIFS('[2]1.1地产销售计划表'!X:X,'[2]1.1地产销售计划表'!B:B,"海沧中心璞盛项目（二期）",'[2]1.1地产销售计划表'!G:G,"商业",'[2]1.1地产销售计划表'!H:H,"签约(元）")/100000000 -> 0 | V10: =SUM(W10:X10) -> 0 | W10: =SUMIFS('[2]1.1地产销售计划表'!Y:Y,'[2]1.1地产销售计划表'!B:B,"海沧中心璞盛项目（一期）",'[2]1.1地产销售计划表'!G:G,"商业",'[2]1.1地产销售计划表'!H:H,"签约(元）")/100000000 -> 0 | X10: =SUMIFS('[2]1.1地产销售计划表'!Y:Y,'[2]1.1地产销售计划表'!B:B,"海沧中心璞盛项目（二期）",'[2]1.1地产销售计划表'!G:G,"商业",'[2]1.1地产销售计划表'!H:H,"签约(元）")/100000000 -> 0 | Y10: =SUM(Z10:AA10) -> 0 | Z10: =SUMIFS('[2]1.1地产销售计划表'!Z:Z,'[2]1.1地产销售计划表'!B:B,"海沧中心璞盛项目（一期）",'[2]1.1地产销售计划表'!G:G,"商业",'[2]1.1地产销售计划表'!H:H,"签约(元）")/100000000 -> 0 | AA10: =SUMIFS('[2]1.1地产销售计划表'!Z:Z,'[2]1.1地产销售计划表'!B:B,"海沧中心璞盛项目（二期）",'[2]1.1地产销售计划表'!G:G,"商业",'[2]1.1地产销售计划表'!H:H,"签约(元）")/100000000 -> 0 | AB10: =SUM(AC10:AD10) -> 0.710247 | AC10: =SUMIFS('[2]1.1地产销售计划表'!AA:AA,'[2]1.1地产销售计划表'!B:B,"海沧中心璞盛项目（一期）",'[2]1.1地产销售计划表'!G:G,"商业",'[2]1.1地产销售计划表'!H:H,"签约(元）")/100000000 -> 0.628269 | AD10: =SUMIFS('[2]1.1地产销售计划表'!AA:AA,'[2]1.1地产销售计划表'!B:B,"海沧中心璞盛项目（二期）",'[2]1.1地产销售计划表'!G:G,"商业",'[2]1.1地产销售计划表'!H:H,"签约(元）")/100000000 -> 0.081978 | AE10: =SUM(AF10:AG10) -> 0 | AF10: =SUMIFS('[2]1.1地产销售计划表'!AB:AB,'[2]1.1地产销售计划表'!B:B,"海沧中心璞盛项目（一期）",'[2]1.1地产销售计划表'!G:G,"商业",'[2]1.1地产销售计划表'!H:H,"签约(元）")/100000000 -> 0 | AG10: =SUMIFS('[2]1.1地产销售计划表'!AB:AB,'[2]1.1地产销售计划表'!B:B,"海沧中心璞盛项目（二期）",'[2]1.1地产销售计划表'!G:G,"商业",'[2]1.1地产销售计划表'!H:H,"签约(元）")/100000000 -> 0
C11: 车位 | D11: =SUM(E11:F11) -> 1.751 | E11: =SUM(H11,Q11,T11,W11,Z11,AC11,AF11) -> 1.4932 | F11: =SUM(I11,R11,U11,X11,AA11,AD11,AG11) -> 0.2578 | G11: =SUM(H11:I11) -> 0.2841 | H11: =(SUMIFS('[2]1.1地产销售计划表'!N:N,'[2]1.1地产销售计划表'!B:B,"海沧中心璞盛项目（一期）",'[2]1.1地产销售计划表'!G:G,"车位",'[2]1.1地产销售计划表'!H:H,"签约(元）")+SUMIFS('[2]1.1地产销售计划表'!V:V,'[2]1.1地产销售计划表'!B:B,"海沧中心璞盛项目（一期）",'[2]1.1地产销售计划表'!G:G,"车位",'[2]1.1地产销售计划表'!H:H,"签约(元）"))/100000000 -> 0.2163 | I11: =(SUMIFS('[2]1.1地产销售计划表'!N:N,'[2]1.1地产销售计划表'!B:B,"海沧中心璞盛项目（二期）",'[2]1.1地产销售计划表'!G:G,"车位",'[2]1.1地产销售计划表'!H:H,"签约(元）")+SUMIFS('[2]1.1地产销售计划表'!V:V,'[2]1.1地产销售计划表'!B:B,"海沧中心璞盛项目（二期）",'[2]1.1地产销售计划表'!G:G,"车位",'[2]1.1地产销售计划表'!H:H,"签约(元）"))/100000000 -> 0.0678 | P11: =SUM(Q11:R11) -> 0.0608 | Q11: =SUMIFS('[2]1.1地产销售计划表'!W:W,'[2]1.1地产销售计划表'!B:B,"海沧中心璞盛项目（一期）",'[2]1.1地产销售计划表'!G:G,"车位",'[2]1.1地产销售计划表'!H:H,"签约(元）")/100000000 -> 0.0608 | R11: =SUMIFS('[2]1.1地产销售计划表'!W:W,'[2]1.1地产销售计划表'!B:B,"海沧中心璞盛项目（二期）",'[2]1.1地产销售计划表'!G:G,"车位",'[2]1.1地产销售计划表'!H:H,"签约(元）")/100000000 -> 0 | S11: =SUM(T11:U11) -> 0.391689 | T11: =SUMIFS('[2]1.1地产销售计划表'!X:X,'[2]1.1地产销售计划表'!B:B,"海沧中心璞盛项目（一期）",'[2]1.1地产销售计划表'!G:G,"车位",'[2]1.1地产销售计划表'!H:H,"签约(元）")/100000000 -> 0.278389 | U11: =SUMIFS('[2]1.1地产销售计划表'!X:X,'[2]1.1地产销售计划表'!B:B,"海沧中心璞盛项目（二期）",'[2]1.1地产销售计划表'!G:G,"车位",'[2]1.1地产销售计划表'!H:H,"签约(元）")/100000000 -> 0.1133 | V11: =SUM(W11:X11) -> 0.442411 | W11: =SUMIFS('[2]1.1地产销售计划表'!Y:Y,'[2]1.1地产销售计划表'!B:B,"海沧中心璞盛项目（一期）",'[2]1.1地产销售计划表'!G:G,"车位",'[2]1.1地产销售计划表'!H:H,"签约(元）")/100000000 -> 0.442411 | X11: =SUMIFS('[2]1.1地产销售计划表'!Y:Y,'[2]1.1地产销售计划表'!B:B,"海沧中心璞盛项目（二期）",'[2]1.1地产销售计划表'!G:G,"车位",'[2]1.1地产销售计划表'!H:H,"签约(元）")/100000000 -> 0 | Y11: =SUM(Z11:AA11) -> 0 | Z11: =SUMIFS('[2]1.1地产销售计划表'!Z:Z,'[2]1.1地产销售计划表'!B:B,"海沧中心璞盛项目（一期）",'[2]1.1地产销售计划表'!G:G,"车位",'[2]1.1地产销售计划表'!H:H,"签约(元）")/100000000 -> 0 | AA11: =SUMIFS('[2]1.1地产销售计划表'!Z:Z,'[2]1.1地产销售计划表'!B:B,"海沧中心璞盛项目（二期）",'[2]1.1地产销售计划表'!G:G,"车位",'[2]1.1地产销售计划表'!H:H,"签约(元）")/100000000 -> 0 | AB11: =SUM(AC11:AD11) -> 0.572 | AC11: =+AC21*AC26/10000 -> 0.4953 | AD11: =+AD21*AD26/10000 -> 0.0767 | AE11: =SUM(AF11:AG11) -> 0 | AF11: =SUMIFS('[2]1.1地产销售计划表'!AB:AB,'[2]1.1地产销售计划表'!B:B,"海沧中心璞盛项目（一期）",'[2]1.1地产销售计划表'!G:G,"车位",'[2]1.1地产销售计划表'!H:H,"签约(元）")/100000000 -> 0 | AG11: =SUMIFS('[2]1.1地产销售计划表'!AB:AB,'[2]1.1地产销售计划表'!B:B,"海沧中心璞盛项目（二期）",'[2]1.1地产销售计划表'!G:G,"车位",'[2]1.1地产销售计划表'!H:H,"签约(元）")/100000000 -> 0
A12: 面积 | C12: 住宅 | D12: =SUM(E12:F12) -> 12.032753 | E12: =SUM(H12,Q12,T12,W12,Z12,AC12,AF12) -> 9.643089 | F12: =SUM(I12,R12,U12,X12,AA12,AD12,AG12) -> 2.389664 | G12: =SUM(H12:I12) -> 8.731332 | H12: =SUM(H13:H14) -> 6.595078 | I12: =SUM(I13:I14) -> 2.136254 | J12: =SUM(J13:J14) -> 0 | K12: =SUM(K13:K14) -> 0 | L12: =SUM(L13:L14) -> 0 | M12: =SUM(M13:M14) -> 0 | N12: =SUM(N13:N14) -> 0 | O12: =SUM(O13:O14) -> 0 | ... AG12: =SUM(AG13:AG14) -> 0
C13: 其中：普宅 | D13: =SUM(E13:F13) -> 9.143207 | E13: =SUM(H13,Q13,T13,W13,Z13,AC13,AF13) -> 6.753543 | F13: =SUM(I13,R13,U13,X13,AA13,AD13,AG13) -> 2.389664 | G13: =SUM(H13:I13) -> 8.731332 | H13: =(SUMIFS('[2]1.1地产销售计划表'!N:N,'[2]1.1地产销售计划表'!B:B,"海沧中心璞盛项目（一期）",'[2]1.1地产销售计划表'!G:G,"住宅-精装普宅",'[2]1.1地产销售计划表'!H:H,"面积（㎡）")+SUMIFS('[2]1.1地产销售计划表'!V:V,'[2]1.1地产销售计划表'!B:B,"海沧中心璞盛项目（一期）",'[2]1.1地产销售计划表'!G:G,"住宅-精装普宅",'[2]1.1地产销售计划表'!H:H,"面积（㎡）"))/10000 -> 6.595078 | I13: =(SUMIFS('[2]1.1地产销售计划表'!N:N,'[2]1.1地产销售计划表'!B:B,"海沧中心璞盛项目（二期）",'[2]1.1地产销售计划表'!G:G,"住宅-精装普宅",'[2]1.1地产销售计划表'!H:H,"面积（㎡）")+SUMIFS('[2]1.1地产销售计划表'!V:V,'[2]1.1地产销售计划表'!B:B,"海沧中心璞盛项目（二期）",'[2]1.1地产销售计划表'!G:G,"住宅-精装普宅",'[2]1.1地产销售计划表'!H:H,"面积（㎡）"))/10000 -> 2.136254 | P13: =SUM(Q13:R13) -> 0.411875 | Q13: =SUMIFS('[2]1.1地产销售计划表'!W:W,'[2]1.1地产销售计划表'!B:B,"海沧中心璞盛项目（一期）",'[2]1.1地产销售计划表'!G:G,"住宅-精装普宅",'[2]1.1地产销售计划表'!H:H,"面积（㎡）")/10000 -> 0.158465 | R13: =SUMIFS('[2]1.1地产销售计划表'!W:W,'[2]1.1地产销售计划表'!B:B,"海沧中心璞盛项目（二期）",'[2]1.1地产销售计划表'!G:G,"住宅-精装普宅",'[2]1.1地产销售计划表'!H:H,"面积（㎡）")/10000 -> 0.25341 | S13: =SUM(T13:U13) -> 0 | T13: =SUMIFS('[2]1.1地产销售计划表'!X:X,'[2]1.1地产销售计划表'!B:B,"海沧中心璞盛项目（一期）",'[2]1.1地产销售计划表'!G:G,"住宅-精装普宅",'[2]1.1地产销售计划表'!H:H,"面积（㎡）")/10000 -> 0 | U13: =SUMIFS('[2]1.1地产销售计划表'!X:X,'[2]1.1地产销售计划表'!B:B,"海沧中心璞盛项目（二期）",'[2]1.1地产销售计划表'!G:G,"住宅-精装普宅",'[2]1.1地产销售计划表'!H:H,"面积（㎡）")/10000 -> 0 | V13: =SUM(W13:X13) -> 0 | W13: =SUMIFS('[2]1.1地产销售计划表'!Y:Y,'[2]1.1地产销售计划表'!B:B,"海沧中心璞盛项目（一期）",'[2]1.1地产销售计划表'!G:G,"住宅-精装普宅",'[2]1.1地产销售计划表'!H:H,"面积（㎡）")/10000 -> 0 | X13: =SUMIFS('[2]1.1地产销售计划表'!Y:Y,'[2]1.1地产销售计划表'!B:B,"海沧中心璞盛项目（二期）",'[2]1.1地产销售计划表'!G:G,"住宅-精装普宅",'[2]1.1地产销售计划表'!H:H,"面积（㎡）")/10000 -> 0 | Y13: =SUM(Z13:AA13) -> 0 | Z13: =SUMIFS('[2]1.1地产销售计划表'!Z:Z,'[2]1.1地产销售计划表'!B:B,"海沧中心璞盛项目（一期）",'[2]1.1地产销售计划表'!G:G,"住宅-精装普宅",'[2]1.1地产销售计划表'!H:H,"面积（㎡）")/10000 -> 0 | AA13: =SUMIFS('[2]1.1地产销售计划表'!Z:Z,'[2]1.1地产销售计划表'!B:B,"海沧中心璞盛项目（二期）",'[2]1.1地产销售计划表'!G:G,"住宅-精装普宅",'[2]1.1地产销售计划表'!H:H,"面积（㎡）")/10000 -> 0 | AB13: =SUM(AC13:AD13) -> 0 | AC13: =SUMIFS('[2]1.1地产销售计划表'!AA:AA,'[2]1.1地产销售计划表'!B:B,"海沧中心璞盛项目（一期）",'[2]1.1地产销售计划表'!G:G,"住宅-精装普宅",'[2]1.1地产销售计划表'!H:H,"面积（㎡）")/10000 -> 0 | AD13: =SUMIFS('[2]1.1地产销售计划表'!AA:AA,'[2]1.1地产销售计划表'!B:B,"海沧中心璞盛项目（二期）",'[2]1.1地产销售计划表'!G:G,"住宅-精装普宅",'[2]1.1地产销售计划表'!H:H,"面积（㎡）")/10000 -> 0 | AE13: =SUM(AF13:AG13) -> 0 | AF13: =SUMIFS('[2]1.1地产销售计划表'!AB:AB,'[2]1.1地产销售计划表'!B:B,"海沧中心璞盛项目（一期）",'[2]1.1地产销售计划表'!G:G,"住宅-精装普宅",'[2]1.1地产销售计划表'!H:H,"面积（㎡）")/10000 -> 0 | AG13: =SUMIFS('[2]1.1地产销售计划表'!AB:AB,'[2]1.1地产销售计划表'!B:B,"海沧中心璞盛项目（二期）",'[2]1.1地产销售计划表'!G:G,"住宅-精装普宅",'[2]1.1地产销售计划表'!H:H,"面积（㎡）")/10000 -> 0
C14: 非普宅 | D14: =SUM(E14:F14) -> 2.889546 | E14: =SUM(H14,Q14,T14,W14,Z14,AC14,AF14) -> 2.889546 | F14: =SUM(I14,R14,U14,X14,AA14,AD14,AG14) -> 0 | G14: =SUM(H14:I14) -> 0 | H14: =(SUMIFS('[2]1.1地产销售计划表'!N:N,'[2]1.1地产销售计划表'!B:B,"海沧中心璞盛项目（一期）",'[2]1.1地产销售计划表'!G:G,"住宅-精装非普宅",'[2]1.1地产销售计划表'!H:H,"面积（㎡）")+SUMIFS('[2]1.1地产销售计划表'!V:V,'[2]1.1地产销售计划表'!B:B,"海沧中心璞盛项目（一期）",'[2]1.1地产销售计划表'!G:G,"住宅-精装非普宅",'[2]1.1地产销售计划表'!H:H,"面积（㎡）"))/10000 -> 0 | I14: =(SUMIFS('[2]1.1地产销售计划表'!N:N,'[2]1.1地产销售计划表'!B:B,"海沧中心璞盛项目（二期）",'[2]1.1地产销售计划表'!G:G,"住宅-精装非普宅",'[2]1.1地产销售计划表'!H:H,"面积（㎡）")+SUMIFS('[2]1.1地产销售计划表'!V:V,'[2]1.1地产销售计划表'!B:B,"海沧中心璞盛项目（二期）",'[2]1.1地产销售计划表'!G:G,"住宅-精装非普宅",'[2]1.1地产销售计划表'!H:H,"面积（㎡）"))/10000 -> 0 | P14: =SUM(Q14:R14) -> 1.7543672 | Q14: =SUMIFS('[2]1.1地产销售计划表'!W:W,'[2]1.1地产销售计划表'!B:B,"海沧中心璞盛项目（一期）",'[2]1.1地产销售计划表'!G:G,"住宅-精装非普宅",'[2]1.1地产销售计划表'!H:H,"面积（㎡）")/10000 -> 1.7543672 | R14: =SUMIFS('[2]1.1地产销售计划表'!W:W,'[2]1.1地产销售计划表'!B:B,"海沧中心璞盛项目（二期）",'[2]1.1地产销售计划表'!G:G,"住宅-精装非普宅",'[2]1.1地产销售计划表'!H:H,"面积（㎡）")/10000 -> 0 | S14: =SUM(T14:U14) -> 1.1351788 | T14: =SUMIFS('[2]1.1地产销售计划表'!X:X,'[2]1.1地产销售计划表'!B:B,"海沧中心璞盛项目（一期）",'[2]1.1地产销售计划表'!G:G,"住宅-精装非普宅",'[2]1.1地产销售计划表'!H:H,"面积（㎡）")/10000 -> 1.1351788 | U14: =SUMIFS('[2]1.1地产销售计划表'!X:X,'[2]1.1地产销售计划表'!B:B,"海沧中心璞盛项目（二期）",'[2]1.1地产销售计划表'!G:G,"住宅-精装非普宅",'[2]1.1地产销售计划表'!H:H,"面积（㎡）")/10000 -> 0 | V14: =SUM(W14:X14) -> 0 | W14: =SUMIFS('[2]1.1地产销售计划表'!Y:Y,'[2]1.1地产销售计划表'!B:B,"海沧中心璞盛项目（一期）",'[2]1.1地产销售计划表'!G:G,"住宅-精装非普宅",'[2]1.1地产销售计划表'!H:H,"面积（㎡）")/10000 -> 0 | X14: =SUMIFS('[2]1.1地产销售计划表'!Y:Y,'[2]1.1地产销售计划表'!B:B,"海沧中心璞盛项目（二期）",'[2]1.1地产销售计划表'!G:G,"住宅-精装非普宅",'[2]1.1地产销售计划表'!H:H,"面积（㎡）")/10000 -> 0 | Y14: =SUM(Z14:AA14) -> 0 | Z14: =SUMIFS('[2]1.1地产销售计划表'!Z:Z,'[2]1.1地产销售计划表'!B:B,"海沧中心璞盛项目（一期）",'[2]1.1地产销售计划表'!G:G,"住宅-精装非普宅",'[2]1.1地产销售计划表'!H:H,"面积（㎡）")/10000 -> 0 | AA14: =SUMIFS('[2]1.1地产销售计划表'!Z:Z,'[2]1.1地产销售计划表'!B:B,"海沧中心璞盛项目（二期）",'[2]1.1地产销售计划表'!G:G,"住宅-精装非普宅",'[2]1.1地产销售计划表'!H:H,"面积（㎡）")/10000 -> 0 | AB14: =SUM(AC14:AD14) -> 0 | AC14: =SUMIFS('[2]1.1地产销售计划表'!AA:AA,'[2]1.1地产销售计划表'!B:B,"海沧中心璞盛项目（一期）",'[2]1.1地产销售计划表'!G:G,"住宅-精装非普宅",'[2]1.1地产销售计划表'!H:H,"面积（㎡）")/10000 -> 0 | AD14: =SUMIFS('[2]1.1地产销售计划表'!AA:AA,'[2]1.1地产销售计划表'!B:B,"海沧中心璞盛项目（二期）",'[2]1.1地产销售计划表'!G:G,"住宅-精装非普宅",'[2]1.1地产销售计划表'!H:H,"面积（㎡）")/10000 -> 0 | AE14: =SUM(AF14:AG14) -> 0 | AF14: =SUMIFS('[2]1.1地产销售计划表'!AB:AB,'[2]1.1地产销售计划表'!B:B,"海沧中心璞盛项目（一期）",'[2]1.1地产销售计划表'!G:G,"住宅-精装非普宅",'[2]1.1地产销售计划表'!H:H,"面积（㎡）")/10000 -> 0 | AG14: =SUMIFS('[2]1.1地产销售计划表'!AB:AB,'[2]1.1地产销售计划表'!B:B,"海沧中心璞盛项目（二期）",'[2]1.1地产销售计划表'!G:G,"住宅-精装非普宅",'[2]1.1地产销售计划表'!H:H,"面积（㎡）")/10000 -> 0
C15: 商业 | D15: =SUM(E15:F15) -> 0.236749 | E15: =SUM(H15,Q15,T15,W15,Z15,AC15,AF15) -> 0.209423 | F15: =SUM(I15,R15,U15,X15,AA15,AD15,AG15) -> 0.027326 | G15: =SUM(H15:I15) -> 0 | H15: =(SUMIFS('[2]1.1地产销售计划表'!N:N,'[2]1.1地产销售计划表'!B:B,"海沧中心璞盛项目（一期）",'[2]1.1地产销售计划表'!G:G,"商业",'[2]1.1地产销售计划表'!H:H,"面积（㎡）")+SUMIFS('[2]1.1地产销售计划表'!V:V,'[2]1.1地产销售计划表'!B:B,"海沧中心璞盛项目（一期）",'[2]1.1地产销售计划表'!G:G,"商业",'[2]1.1地产销售计划表'!H:H,"面积（㎡）"))/10000 -> 0 | I15: =(SUMIFS('[2]1.1地产销售计划表'!N:N,'[2]1.1地产销售计划表'!B:B,"海沧中心璞盛项目（二期）",'[2]1.1地产销售计划表'!G:G,"商业",'[2]1.1地产销售计划表'!H:H,"面积（㎡）")+SUMIFS('[2]1.1地产销售计划表'!V:V,'[2]1.1地产销售计划表'!B:B,"海沧中心璞盛项目（二期）",'[2]1.1地产销售计划表'!G:G,"商业",'[2]1.1地产销售计划表'!H:H,"面积（㎡）"))/10000 -> 0 | P15: =SUM(Q15:R15) -> 0 | Q15: =SUMIFS('[2]1.1地产销售计划表'!W:W,'[2]1.1地产销售计划表'!B:B,"海沧中心璞盛项目（一期）",'[2]1.1地产销售计划表'!G:G,"商业",'[2]1.1地产销售计划表'!H:H,"面积（㎡）")/10000 -> 0 | R15: =SUMIFS('[2]1.1地产销售计划表'!W:W,'[2]1.1地产销售计划表'!B:B,"海沧中心璞盛项目（二期）",'[2]1.1地产销售计划表'!G:G,"商业",'[2]1.1地产销售计划表'!H:H,"面积（㎡）")/10000 -> 0 | S15: =SUM(T15:U15) -> 0 | T15: =SUMIFS('[2]1.1地产销售计划表'!X:X,'[2]1.1地产销售计划表'!B:B,"海沧中心璞盛项目（一期）",'[2]1.1地产销售计划表'!G:G,"商业",'[2]1.1地产销售计划表'!H:H,"面积（㎡）")/10000 -> 0 | U15: =SUMIFS('[2]1.1地产销售计划表'!X:X,'[2]1.1地产销售计划表'!B:B,"海沧中心璞盛项目（二期）",'[2]1.1地产销售计划表'!G:G,"商业",'[2]1.1地产销售计划表'!H:H,"面积（㎡）")/10000 -> 0 | V15: =SUM(W15:X15) -> 0 | W15: =SUMIFS('[2]1.1地产销售计划表'!Y:Y,'[2]1.1地产销售计划表'!B:B,"海沧中心璞盛项目（一期）",'[2]1.1地产销售计划表'!G:G,"商业",'[2]1.1地产销售计划表'!H:H,"面积（㎡）")/10000 -> 0 | X15: =SUMIFS('[2]1.1地产销售计划表'!Y:Y,'[2]1.1地产销售计划表'!B:B,"海沧中心璞盛项目（二期）",'[2]1.1地产销售计划表'!G:G,"商业",'[2]1.1地产销售计划表'!H:H,"面积（㎡）")/10000 -> 0 | Y15: =SUM(Z15:AA15) -> 0 | Z15: =SUMIFS('[2]1.1地产销售计划表'!Z:Z,'[2]1.1地产销售计划表'!B:B,"海沧中心璞盛项目（一期）",'[2]1.1地产销售计划表'!G:G,"商业",'[2]1.1地产销售计划表'!H:H,"面积（㎡）")/10000 -> 0 | AA15: =SUMIFS('[2]1.1地产销售计划表'!Z:Z,'[2]1.1地产销售计划表'!B:B,"海沧中心璞盛项目（二期）",'[2]1.1地产销售计划表'!G:G,"商业",'[2]1.1地产销售计划表'!H:H,"面积（㎡）")/10000 -> 0 | AB15: =SUM(AC15:AD15) -> 0.236749 | AC15: =SUMIFS('[2]1.1地产销售计划表'!AA:AA,'[2]1.1地产销售计划表'!B:B,"海沧中心璞盛项目（一期）",'[2]1.1地产销售计划表'!G:G,"商业",'[2]1.1地产销售计划表'!H:H,"面积（㎡）")/10000 -> 0.209423 | AD15: =SUMIFS('[2]1.1地产销售计划表'!AA:AA,'[2]1.1地产销售计划表'!B:B,"海沧中心璞盛项目（二期）",'[2]1.1地产销售计划表'!G:G,"商业",'[2]1.1地产销售计划表'!H:H,"面积（㎡）")/10000 -> 0.027326 | AE15: =SUM(AF15:AG15) -> 0 | AF15: =SUMIFS('[2]1.1地产销售计划表'!AB:AB,'[2]1.1地产销售计划表'!B:B,"海沧中心璞盛项目（一期）",'[2]1.1地产销售计划表'!G:G,"商业",'[2]1.1地产销售计划表'!H:H,"面积（㎡）")/10000 -> 0 | AG15: =SUMIFS('[2]1.1地产销售计划表'!AB:AB,'[2]1.1地产销售计划表'!B:B,"海沧中心璞盛项目（二期）",'[2]1.1地产销售计划表'!G:G,"商业",'[2]1.1地产销售计划表'!H:H,"面积（㎡）")/10000 -> 0
C16: 车位 | D16: =SUM(E16:F16) -> 3.5963006 | E16: =SUM(H16,Q16,T16,W16,Z16,AC16,AF16) -> 3.033058 | F16: =SUM(I16,R16,U16,X16,AA16,AD16,AG16) -> 0.56324258 | G16: =SUM(H16:I16) -> 0.402369 | H16: =(SUMIFS('[2]1.1地产销售计划表'!N:N,'[2]1.1地产销售计划表'!B:B,"海沧中心璞盛项目（一期）",'[2]1.1地产销售计划表'!G:G,"车位",'[2]1.1地产销售计划表'!H:H,"面积（㎡）")+SUMIFS('[2]1.1地产销售计划表'!V:V,'[2]1.1地产销售计划表'!B:B,"海沧中心璞盛项目（一期）",'[2]1.1地产销售计划表'!G:G,"车位",'[2]1.1地产销售计划表'!H:H,"面积（㎡）"))/10000 -> 0.312405 | I16: =(SUMIFS('[2]1.1地产销售计划表'!N:N,'[2]1.1地产销售计划表'!B:B,"海沧中心璞盛项目（二期）",'[2]1.1地产销售计划表'!G:G,"车位",'[2]1.1地产销售计划表'!H:H,"面积（㎡）")+SUMIFS('[2]1.1地产销售计划表'!V:V,'[2]1.1地产销售计划表'!B:B,"海沧中心璞盛项目（二期）",'[2]1.1地产销售计划表'!G:G,"车位",'[2]1.1地产销售计划表'!H:H,"面积（㎡）"))/10000 -> 0.089964 | P16: =SUM(Q16:R16) -> 0.122094 | Q16: =SUMIFS('[2]1.1地产销售计划表'!W:W,'[2]1.1地产销售计划表'!B:B,"海沧中心璞盛项目（一期）",'[2]1.1地产销售计划表'!G:G,"车位",'[2]1.1地产销售计划表'!H:H,"面积（㎡）")/10000 -> 0.122094 | R16: =SUMIFS('[2]1.1地产销售计划表'!W:W,'[2]1.1地产销售计划表'!B:B,"海沧中心璞盛项目（二期）",'[2]1.1地产销售计划表'!G:G,"车位",'[2]1.1地产销售计划表'!H:H,"面积（㎡）")/10000 -> 0 | S16: =SUM(T16:U16) -> 0.740981 | T16: =SUMIFS('[2]1.1地产销售计划表'!X:X,'[2]1.1地产销售计划表'!B:B,"海沧中心璞盛项目（一期）",'[2]1.1地产销售计划表'!G:G,"车位",'[2]1.1地产销售计划表'!H:H,"面积（㎡）")/10000 -> 0.536571 | U16: =SUMIFS('[2]1.1地产销售计划表'!X:X,'[2]1.1地产销售计划表'!B:B,"海沧中心璞盛项目（二期）",'[2]1.1地产销售计划表'!G:G,"车位",'[2]1.1地产销售计划表'!H:H,"面积（㎡）")/10000 -> 0.20441 | V16: =SUM(W16:X16) -> 0.862566 | W16: =SUMIFS('[2]1.1地产销售计划表'!Y:Y,'[2]1.1地产销售计划表'!B:B,"海沧中心璞盛项目（一期）",'[2]1.1地产销售计划表'!G:G,"车位",'[2]1.1地产销售计划表'!H:H,"面积（㎡）")/10000 -> 0.862566 | X16: =SUMIFS('[2]1.1地产销售计划表'!Y:Y,'[2]1.1地产销售计划表'!B:B,"海沧中心璞盛项目（二期）",'[2]1.1地产销售计划表'!G:G,"车位",'[2]1.1地产销售计划表'!H:H,"面积（㎡）")/10000 -> 0 | Y16: =SUM(Z16:AA16) -> 0 | Z16: =SUMIFS('[2]1.1地产销售计划表'!Z:Z,'[2]1.1地产销售计划表'!B:B,"海沧中心璞盛项目（一期）",'[2]1.1地产销售计划表'!G:G,"车位",'[2]1.1地产销售计划表'!H:H,"面积（㎡）")/10000 -> 0 | AA16: =SUMIFS('[2]1.1地产销售计划表'!Z:Z,'[2]1.1地产销售计划表'!B:B,"海沧中心璞盛项目（二期）",'[2]1.1地产销售计划表'!G:G,"车位",'[2]1.1地产销售计划表'!H:H,"面积（㎡）")/10000 -> 0 | AB16: =SUM(AC16:AD16) -> 1.4682906 | AC16: =+AC21*N61/10000 -> 1.199422 | AD16: =+AD21*N67/10000 -> 0.26886858 | AE16: =SUM(AF16:AG16) -> 0 | AF16: =SUMIFS('[2]1.1地产销售计划表'!AB:AB,'[2]1.1地产销售计划表'!B:B,"海沧中心璞盛项目（一期）",'[2]1.1地产销售计划表'!G:G,"车位",'[2]1.1地产销售计划表'!H:H,"面积（㎡）")/10000 -> 0 | AG16: =SUMIFS('[2]1.1地产销售计划表'!AB:AB,'[2]1.1地产销售计划表'!B:B,"海沧中心璞盛项目（二期）",'[2]1.1地产销售计划表'!G:G,"车位",'[2]1.1地产销售计划表'!H:H,"面积（㎡）")/10000 -> 0
A17: 套数 | C17: 住宅 | D17: =SUM(E17:F17) -> 1055 | E17: =SUM(H17,Q17,T17,W17,Z17,AC17,AF17) -> 828 | F17: =SUM(I17,R17,U17,X17,AA17,AD17,AG17) -> 227 | G17: =SUM(H17:I17) -> 856 | H17: =SUM(H18:H19) -> 648 | I17: =SUM(I18:I19) -> 208 | J17: =SUM(J18:J19) -> 0 | K17: =SUM(K18:K19) -> 0 | L17: =SUM(L18:L19) -> 0 | M17: =SUM(M18:M19) -> 0 | N17: =SUM(N18:N19) -> 0 | O17: =SUM(O18:O19) -> 0 | ... AG17: =SUM(AG18:AG19) -> 0
C18: 其中：普宅 | D18: =SUM(E18:F18) -> 887 | E18: =SUM(H18,Q18,T18,W18,Z18,AC18,AF18) -> 660 | F18: =SUM(I18,R18,U18,X18,AA18,AD18,AG18) -> 227 | G18: =SUM(H18:I18) -> 856 | H18: =SUMIFS('[2]1.1地产销售计划表'!N:N,'[2]1.1地产销售计划表'!B:B,"海沧中心璞盛项目（一期）",'[2]1.1地产销售计划表'!G:G,"住宅-精装普宅",'[2]1.1地产销售计划表'!H:H,"套数（套）")+SUMIFS('[2]1.1地产销售计划表'!V:V,'[2]1.1地产销售计划表'!B:B,"海沧中心璞盛项目（一期）",'[2]1.1地产销售计划表'!G:G,"住宅-精装普宅",'[2]1.1地产销售计划表'!H:H,"套数（套）") -> 648 | I18: =SUMIFS('[2]1.1地产销售计划表'!N:N,'[2]1.1地产销售计划表'!B:B,"海沧中心璞盛项目（二期）",'[2]1.1地产销售计划表'!G:G,"住宅-精装普宅",'[2]1.1地产销售计划表'!H:H,"套数（套）")+SUMIFS('[2]1.1地产销售计划表'!V:V,'[2]1.1地产销售计划表'!B:B,"海沧中心璞盛项目（二期）",'[2]1.1地产销售计划表'!G:G,"住宅-精装普宅",'[2]1.1地产销售计划表'!H:H,"套数（套）") -> 208 | P18: =SUM(Q18:R18) -> 31 | Q18: =SUMIFS('[2]1.1地产销售计划表'!W:W,'[2]1.1地产销售计划表'!B:B,"海沧中心璞盛项目（一期）",'[2]1.1地产销售计划表'!G:G,"住宅-精装普宅",'[2]1.1地产销售计划表'!H:H,"套数（套）") -> 12 | R18: =SUMIFS('[2]1.1地产销售计划表'!W:W,'[2]1.1地产销售计划表'!B:B,"海沧中心璞盛项目（二期）",'[2]1.1地产销售计划表'!G:G,"住宅-精装普宅",'[2]1.1地产销售计划表'!H:H,"套数（套）") -> 19 | S18: =SUM(T18:U18) -> 0 | T18: =SUMIFS('[2]1.1地产销售计划表'!X:X,'[2]1.1地产销售计划表'!B:B,"海沧中心璞盛项目（一期）",'[2]1.1地产销售计划表'!G:G,"住宅-精装普宅",'[2]1.1地产销售计划表'!H:H,"套数（套）") -> 0 | U18: =SUMIFS('[2]1.1地产销售计划表'!X:X,'[2]1.1地产销售计划表'!B:B,"海沧中心璞盛项目（二期）",'[2]1.1地产销售计划表'!G:G,"住宅-精装普宅",'[2]1.1地产销售计划表'!H:H,"套数（套）") -> 0 | V18: =SUM(W18:X18) -> 0 | W18: =SUMIFS('[2]1.1地产销售计划表'!Y:Y,'[2]1.1地产销售计划表'!B:B,"海沧中心璞盛项目（一期）",'[2]1.1地产销售计划表'!G:G,"住宅-精装普宅",'[2]1.1地产销售计划表'!H:H,"套数（套）") -> 0 | X18: =SUMIFS('[2]1.1地产销售计划表'!Y:Y,'[2]1.1地产销售计划表'!B:B,"海沧中心璞盛项目（二期）",'[2]1.1地产销售计划表'!G:G,"住宅-精装普宅",'[2]1.1地产销售计划表'!H:H,"套数（套）") -> 0 | Y18: =SUM(Z18:AA18) -> 0 | Z18: =SUMIFS('[2]1.1地产销售计划表'!Z:Z,'[2]1.1地产销售计划表'!B:B,"海沧中心璞盛项目（一期）",'[2]1.1地产销售计划表'!G:G,"住宅-精装普宅",'[2]1.1地产销售计划表'!H:H,"套数（套）") -> 0 | AA18: =SUMIFS('[2]1.1地产销售计划表'!Z:Z,'[2]1.1地产销售计划表'!B:B,"海沧中心璞盛项目（二期）",'[2]1.1地产销售计划表'!G:G,"住宅-精装普宅",'[2]1.1地产销售计划表'!H:H,"套数（套）") -> 0 | AB18: =SUM(AC18:AD18) -> 0 | AC18: =SUMIFS('[2]1.1地产销售计划表'!AA:AA,'[2]1.1地产销售计划表'!B:B,"海沧中心璞盛项目（一期）",'[2]1.1地产销售计划表'!G:G,"住宅-精装普宅",'[2]1.1地产销售计划表'!H:H,"套数（套）") -> 0 | AD18: =SUMIFS('[2]1.1地产销售计划表'!AA:AA,'[2]1.1地产销售计划表'!B:B,"海沧中心璞盛项目（二期）",'[2]1.1地产销售计划表'!G:G,"住宅-精装普宅",'[2]1.1地产销售计划表'!H:H,"套数（套）") -> 0 | AE18: =SUM(AF18:AG18) -> 0 | AF18: =SUMIFS('[2]1.1地产销售计划表'!AB:AB,'[2]1.1地产销售计划表'!B:B,"海沧中心璞盛项目（一期）",'[2]1.1地产销售计划表'!G:G,"住宅-精装普宅",'[2]1.1地产销售计划表'!H:H,"套数（套）") -> 0 | AG18: =SUMIFS('[2]1.1地产销售计划表'!AB:AB,'[2]1.1地产销售计划表'!B:B,"海沧中心璞盛项目（二期）",'[2]1.1地产销售计划表'!G:G,"住宅-精装普宅",'[2]1.1地产销售计划表'!H:H,"套数（套）") -> 0
C19: 非普宅 | D19: =SUM(E19:F19) -> 168 | E19: =SUM(H19,Q19,T19,W19,Z19,AC19,AF19) -> 168 | F19: =SUM(I19,R19,U19,X19,AA19,AD19,AG19) -> 0 | G19: =SUM(H19:I19) -> 0 | H19: =SUMIFS('[2]1.1地产销售计划表'!N:N,'[2]1.1地产销售计划表'!B:B,"海沧中心璞盛项目（一期）",'[2]1.1地产销售计划表'!G:G,"住宅-精装非普宅",'[2]1.1地产销售计划表'!H:H,"套数（套）")+SUMIFS('[2]1.1地产销售计划表'!V:V,'[2]1.1地产销售计划表'!B:B,"海沧中心璞盛项目（一期）",'[2]1.1地产销售计划表'!G:G,"住宅-精装非普宅",'[2]1.1地产销售计划表'!H:H,"套数（套）") -> 0 | I19: =SUMIFS('[2]1.1地产销售计划表'!N:N,'[2]1.1地产销售计划表'!B:B,"海沧中心璞盛项目（二期）",'[2]1.1地产销售计划表'!G:G,"住宅-精装非普宅",'[2]1.1地产销售计划表'!H:H,"套数（套）")+SUMIFS('[2]1.1地产销售计划表'!V:V,'[2]1.1地产销售计划表'!B:B,"海沧中心璞盛项目（二期）",'[2]1.1地产销售计划表'!G:G,"住宅-精装非普宅",'[2]1.1地产销售计划表'!H:H,"套数（套）") -> 0 | P19: =SUM(Q19:R19) -> 102 | Q19: =SUMIFS('[2]1.1地产销售计划表'!W:W,'[2]1.1地产销售计划表'!B:B,"海沧中心璞盛项目（一期）",'[2]1.1地产销售计划表'!G:G,"住宅-精装非普宅",'[2]1.1地产销售计划表'!H:H,"套数（套）") -> 102 | R19: =SUMIFS('[2]1.1地产销售计划表'!W:W,'[2]1.1地产销售计划表'!B:B,"海沧中心璞盛项目（二期）",'[2]1.1地产销售计划表'!G:G,"住宅-精装非普宅",'[2]1.1地产销售计划表'!H:H,"套数（套）") -> 0 | S19: =SUM(T19:U19) -> 66 | T19: =SUMIFS('[2]1.1地产销售计划表'!X:X,'[2]1.1地产销售计划表'!B:B,"海沧中心璞盛项目（一期）",'[2]1.1地产销售计划表'!G:G,"住宅-精装非普宅",'[2]1.1地产销售计划表'!H:H,"套数（套）") -> 66 | U19: =SUMIFS('[2]1.1地产销售计划表'!X:X,'[2]1.1地产销售计划表'!B:B,"海沧中心璞盛项目（二期）",'[2]1.1地产销售计划表'!G:G,"住宅-精装非普宅",'[2]1.1地产销售计划表'!H:H,"套数（套）") -> 0 | V19: =SUM(W19:X19) -> 0 | W19: =SUMIFS('[2]1.1地产销售计划表'!Y:Y,'[2]1.1地产销售计划表'!B:B,"海沧中心璞盛项目（一期）",'[2]1.1地产销售计划表'!G:G,"住宅-精装非普宅",'[2]1.1地产销售计划表'!H:H,"套数（套）") -> 0 | X19: =SUMIFS('[2]1.1地产销售计划表'!Y:Y,'[2]1.1地产销售计划表'!B:B,"海沧中心璞盛项目（二期）",'[2]1.1地产销售计划表'!G:G,"住宅-精装非普宅",'[2]1.1地产销售计划表'!H:H,"套数（套）") -> 0 | Y19: =SUM(Z19:AA19) -> 0 | Z19: =SUMIFS('[2]1.1地产销售计划表'!Z:Z,'[2]1.1地产销售计划表'!B:B,"海沧中心璞盛项目（一期）",'[2]1.1地产销售计划表'!G:G,"住宅-精装非普宅",'[2]1.1地产销售计划表'!H:H,"套数（套）") -> 0 | AA19: =SUMIFS('[2]1.1地产销售计划表'!Z:Z,'[2]1.1地产销售计划表'!B:B,"海沧中心璞盛项目（二期）",'[2]1.1地产销售计划表'!G:G,"住宅-精装非普宅",'[2]1.1地产销售计划表'!H:H,"套数（套）") -> 0 | AB19: =SUM(AC19:AD19) -> 0 | AC19: =SUMIFS('[2]1.1地产销售计划表'!AA:AA,'[2]1.1地产销售计划表'!B:B,"海沧中心璞盛项目（一期）",'[2]1.1地产销售计划表'!G:G,"住宅-精装非普宅",'[2]1.1地产销售计划表'!H:H,"套数（套）") -> 0 | AD19: =SUMIFS('[2]1.1地产销售计划表'!AA:AA,'[2]1.1地产销售计划表'!B:B,"海沧中心璞盛项目（二期）",'[2]1.1地产销售计划表'!G:G,"住宅-精装非普宅",'[2]1.1地产销售计划表'!H:H,"套数（套）") -> 0 | AE19: =SUM(AF19:AG19) -> 0 | AF19: =SUMIFS('[2]1.1地产销售计划表'!AB:AB,'[2]1.1地产销售计划表'!B:B,"海沧中心璞盛项目（一期）",'[2]1.1地产销售计划表'!G:G,"住宅-精装非普宅",'[2]1.1地产销售计划表'!H:H,"套数（套）") -> 0 | AG19: =SUMIFS('[2]1.1地产销售计划表'!AB:AB,'[2]1.1地产销售计划表'!B:B,"海沧中心璞盛项目（二期）",'[2]1.1地产销售计划表'!G:G,"住宅-精装非普宅",'[2]1.1地产销售计划表'!H:H,"套数（套）") -> 0
C20: 商业 | D20: =SUM(E20:F20) -> 51 | E20: =SUM(H20,Q20,T20,W20,Z20,AC20,AF20) -> 44 | F20: =SUM(I20,R20,U20,X20,AA20,AD20,AG20) -> 7 | G20: =SUM(H20:I20) -> 0 | H20: =SUMIFS('[2]1.1地产销售计划表'!N:N,'[2]1.1地产销售计划表'!B:B,"海沧中心璞盛项目（一期）",'[2]1.1地产销售计划表'!G:G,"商业",'[2]1.1地产销售计划表'!H:H,"套数（套）")+SUMIFS('[2]1.1地产销售计划表'!V:V,'[2]1.1地产销售计划表'!B:B,"海沧中心璞盛项目（一期）",'[2]1.1地产销售计划表'!G:G,"商业",'[2]1.1地产销售计划表'!H:H,"套数（套）") -> 0 | I20: =SUMIFS('[2]1.1地产销售计划表'!N:N,'[2]1.1地产销售计划表'!B:B,"海沧中心璞盛项目（二期）",'[2]1.1地产销售计划表'!G:G,"商业",'[2]1.1地产销售计划表'!H:H,"套数（套）")+SUMIFS('[2]1.1地产销售计划表'!V:V,'[2]1.1地产销售计划表'!B:B,"海沧中心璞盛项目（二期）",'[2]1.1地产销售计划表'!G:G,"商业",'[2]1.1地产销售计划表'!H:H,"套数（套）") -> 0 | P20: =SUM(Q20:R20) -> 0 | Q20: =SUMIFS('[2]1.1地产销售计划表'!W:W,'[2]1.1地产销售计划表'!B:B,"海沧中心璞盛项目（一期）",'[2]1.1地产销售计划表'!G:G,"商业",'[2]1.1地产销售计划表'!H:H,"套数（套）") -> 0 | R20: =SUMIFS('[2]1.1地产销售计划表'!W:W,'[2]1.1地产销售计划表'!B:B,"海沧中心璞盛项目（二期）",'[2]1.1地产销售计划表'!G:G,"商业",'[2]1.1地产销售计划表'!H:H,"套数（套）") -> 0 | S20: =SUM(T20:U20) -> 0 | T20: =SUMIFS('[2]1.1地产销售计划表'!X:X,'[2]1.1地产销售计划表'!B:B,"海沧中心璞盛项目（一期）",'[2]1.1地产销售计划表'!G:G,"商业",'[2]1.1地产销售计划表'!H:H,"套数（套）") -> 0 | U20: =SUMIFS('[2]1.1地产销售计划表'!X:X,'[2]1.1地产销售计划表'!B:B,"海沧中心璞盛项目（二期）",'[2]1.1地产销售计划表'!G:G,"商业",'[2]1.1地产销售计划表'!H:H,"套数（套）") -> 0 | V20: =SUM(W20:X20) -> 0 | W20: =SUMIFS('[2]1.1地产销售计划表'!Y:Y,'[2]1.1地产销售计划表'!B:B,"海沧中心璞盛项目（一期）",'[2]1.1地产销售计划表'!G:G,"商业",'[2]1.1地产销售计划表'!H:H,"套数（套）") -> 0 | X20: =SUMIFS('[2]1.1地产销售计划表'!Y:Y,'[2]1.1地产销售计划表'!B:B,"海沧中心璞盛项目（二期）",'[2]1.1地产销售计划表'!G:G,"商业",'[2]1.1地产销售计划表'!H:H,"套数（套）") -> 0 | Y20: =SUM(Z20:AA20) -> 0 | Z20: =SUMIFS('[2]1.1地产销售计划表'!Z:Z,'[2]1.1地产销售计划表'!B:B,"海沧中心璞盛项目（一期）",'[2]1.1地产销售计划表'!G:G,"商业",'[2]1.1地产销售计划表'!H:H,"套数（套）") -> 0 | AA20: =SUMIFS('[2]1.1地产销售计划表'!Z:Z,'[2]1.1地产销售计划表'!B:B,"海沧中心璞盛项目（二期）",'[2]1.1地产销售计划表'!G:G,"商业",'[2]1.1地产销售计划表'!H:H,"套数（套）") -> 0 | AB20: =SUM(AC20:AD20) -> 51 | AC20: =SUMIFS('[2]1.1地产销售计划表'!AA:AA,'[2]1.1地产销售计划表'!B:B,"海沧中心璞盛项目（一期）",'[2]1.1地产销售计划表'!G:G,"商业",'[2]1.1地产销售计划表'!H:H,"套数（套）") -> 44 | AD20: =SUMIFS('[2]1.1地产销售计划表'!AA:AA,'[2]1.1地产销售计划表'!B:B,"海沧中心璞盛项目（二期）",'[2]1.1地产销售计划表'!G:G,"商业",'[2]1.1地产销售计划表'!H:H,"套数（套）") -> 7 | AE20: =SUM(AF20:AG20) -> 0 | AF20: =SUMIFS('[2]1.1地产销售计划表'!AB:AB,'[2]1.1地产销售计划表'!B:B,"海沧中心璞盛项目（一期）",'[2]1.1地产销售计划表'!G:G,"商业",'[2]1.1地产销售计划表'!H:H,"套数（套）") -> 0 | AG20: =SUMIFS('[2]1.1地产销售计划表'!AB:AB,'[2]1.1地产销售计划表'!B:B,"海沧中心璞盛项目（二期）",'[2]1.1地产销售计划表'!G:G,"商业",'[2]1.1地产销售计划表'!H:H,"套数（套）") -> 0
C21: 车位 | D21: =SUM(E21:F21) -> 1090 | E21: =SUM(H21,Q21,T21,W21,Z21,AC21,AF21) -> 942 | F21: =SUM(I21,R21,U21,X21,AA21,AD21,AG21) -> 148 | G21: =SUM(H21:I21) -> 110 | H21: =SUMIFS('[2]1.1地产销售计划表'!N:N,'[2]1.1地产销售计划表'!B:B,"海沧中心璞盛项目（一期）",'[2]1.1地产销售计划表'!G:G,"车位",'[2]1.1地产销售计划表'!H:H,"套数（套）")+SUMIFS('[2]1.1地产销售计划表'!V:V,'[2]1.1地产销售计划表'!B:B,"海沧中心璞盛项目（一期）",'[2]1.1地产销售计划表'!G:G,"车位",'[2]1.1地产销售计划表'!H:H,"套数（套）") -> 84 | I21: =SUMIFS('[2]1.1地产销售计划表'!N:N,'[2]1.1地产销售计划表'!B:B,"海沧中心璞盛项目（二期）",'[2]1.1地产销售计划表'!G:G,"车位",'[2]1.1地产销售计划表'!H:H,"套数（套）")+SUMIFS('[2]1.1地产销售计划表'!V:V,'[2]1.1地产销售计划表'!B:B,"海沧中心璞盛项目（二期）",'[2]1.1地产销售计划表'!G:G,"车位",'[2]1.1地产销售计划表'!H:H,"套数（套）") -> 26 | P21: =SUM(Q21:R21) -> 38 | Q21: =SUMIFS('[2]1.1地产销售计划表'!W:W,'[2]1.1地产销售计划表'!B:B,"海沧中心璞盛项目（一期）",'[2]1.1地产销售计划表'!G:G,"车位",'[2]1.1地产销售计划表'!H:H,"套数（套）") -> 38 | R21: =SUMIFS('[2]1.1地产销售计划表'!W:W,'[2]1.1地产销售计划表'!B:B,"海沧中心璞盛项目（二期）",'[2]1.1地产销售计划表'!G:G,"车位",'[2]1.1地产销售计划表'!H:H,"套数（套）") -> 0 | S21: =SUM(T21:U21) -> 230 | T21: =SUMIFS('[2]1.1地产销售计划表'!X:X,'[2]1.1地产销售计划表'!B:B,"海沧中心璞盛项目（一期）",'[2]1.1地产销售计划表'!G:G,"车位",'[2]1.1地产销售计划表'!H:H,"套数（套）") -> 167 | U21: =SUMIFS('[2]1.1地产销售计划表'!X:X,'[2]1.1地产销售计划表'!B:B,"海沧中心璞盛项目（二期）",'[2]1.1地产销售计划表'!G:G,"车位",'[2]1.1地产销售计划表'!H:H,"套数（套）") -> 63 | V21: =SUM(W21:X21) -> 272 | W21: =SUMIFS('[2]1.1地产销售计划表'!Y:Y,'[2]1.1地产销售计划表'!B:B,"海沧中心璞盛项目（一期）",'[2]1.1地产销售计划表'!G:G,"车位",'[2]1.1地产销售计划表'!H:H,"套数（套）") -> 272 | X21: =SUMIFS('[2]1.1地产销售计划表'!Y:Y,'[2]1.1地产销售计划表'!B:B,"海沧中心璞盛项目（二期）",'[2]1.1地产销售计划表'!G:G,"车位",'[2]1.1地产销售计划表'!H:H,"套数（套）") -> 0 | Y21: =SUM(Z21:AA21) -> 0 | Z21: =SUMIFS('[2]1.1地产销售计划表'!Z:Z,'[2]1.1地产销售计划表'!B:B,"海沧中心璞盛项目（一期）",'[2]1.1地产销售计划表'!G:G,"车位",'[2]1.1地产销售计划表'!H:H,"套数（套）") -> 0 | AA21: =SUMIFS('[2]1.1地产销售计划表'!Z:Z,'[2]1.1地产销售计划表'!B:B,"海沧中心璞盛项目（二期）",'[2]1.1地产销售计划表'!G:G,"车位",'[2]1.1地产销售计划表'!H:H,"套数（套）") -> 0 | AB21: =SUM(AC21:AD21) -> 440 | AC21: 381 | AD21: 59 | AE21: =SUM(AF21:AG21) -> 0 | AF21: =SUMIFS('[2]1.1地产销售计划表'!AB:AB,'[2]1.1地产销售计划表'!B:B,"海沧中心璞盛项目（一期）",'[2]1.1地产销售计划表'!G:G,"车位",'[2]1.1地产销售计划表'!H:H,"套数（套）") -> 0 | AG21: =SUMIFS('[2]1.1地产销售计划表'!AB:AB,'[2]1.1地产销售计划表'!B:B,"海沧中心璞盛项目（二期）",'[2]1.1地产销售计划表'!G:G,"车位",'[2]1.1地产销售计划表'!H:H,"套数（套）") -> 0
A22: 均价 | C22: 住宅 | D22: =IFERROR(+D7/D12,0) -> 3.2933628 | E22: =IFERROR(+E7/E12,0) -> 3.2595304 | F22: =IFERROR(+F7/F12,0) -> 3.4298877 | G22: =IFERROR(+G7/G12,0) -> 3.3500315 | H22: =IFERROR(+H7/H12,0) -> 3.3195124 | I22: =IFERROR(+I7/I12,0) -> 3.4442506 | J22: =IFERROR(+J7/J12,0) -> 0 | K22: =IFERROR(+K7/K12,0) -> 0 | ... AG22: =IFERROR(+AG7/AG12,0) -> 0
C23: 其中：普宅 | D23: =IFERROR(+D8/D13,0) -> 3.3508475 | E23: =IFERROR(+E8/E13,0) -> 3.32288 | F23: =IFERROR(+F8/F13,0) -> 3.4298877 | G23: =IFERROR(+G8/G13,0) -> 3.3500315 | H23: =IFERROR(+H8/H13,0) -> 3.3195124 | I23: =IFERROR(+I8/I13,0) -> 3.4442506 | J23: =IFERROR(+J8/J13,0) -> 0 | K23: =IFERROR(+K8/K13,0) -> 0 | ... AG23: =IFERROR(+AG8/AG13,0) -> 0
C24: 非普宅 | D24: =IFERROR(+D9/D14,0) -> 3.1114677 | E24: =IFERROR(+E9/E14,0) -> 3.1114677 | F24: =IFERROR(+F9/F14,0) -> 0 | G24: =IFERROR(+G9/G14,0) -> 0 | H24: =IFERROR(+H9/H14,0) -> 0 | I24: =IFERROR(+I9/I14,0) -> 0 | J24: =IFERROR(+J9/J14,0) -> 0 | K24: =IFERROR(+K9/K14,0) -> 0 | ... AG24: =IFERROR(+AG9/AG14,0) -> 0
C25: 商业 | D25: =IFERROR(+D10/D15,0) -> 3 | E25: =IFERROR(+E10/E15,0) -> 3 | F25: =IFERROR(+F10/F15,0) -> 3 | G25: =IFERROR(+G10/G15,0) -> 0 | H25: =IFERROR(+H10/H15,0) -> 0 | I25: =IFERROR(+I10/I15,0) -> 0 | J25: =IFERROR(+J10/J15,0) -> 0 | K25: =IFERROR(+K10/K15,0) -> 0 | ... AG25: =IFERROR(+AG10/AG15,0) -> 0
C26: 车位（万元/个） | D26: =IFERROR(+D11/D21,0)*10000 -> 16.06422 | E26: =IFERROR(+E11/E21,0)*10000 -> 15.85138 | F26: =IFERROR(+F11/F21,0)*10000 -> 17.418919 | G26: =IFERROR(+G11/G21,0)*10000 -> 25.827273 | H26: =IFERROR(+H11/H21,0)*10000 -> 25.75 | I26: =IFERROR(+I11/I21,0)*10000 -> 26.076923 | J26: =IFERROR(+J11/J21,0)*10000 -> 0 | K26: =IFERROR(+K11/K21,0)*10000 -> 0 | ... AB26: =IFERROR(+AB11/AB21,0)*10000 -> 13 | AC26: 13 | AD26: =+AC26 -> 13 | AE26: =IFERROR(+AE11/AE21,0)*10000 -> 0 | AF26: =IFERROR(+AF11/AF21,0)*10000 -> 0 | AG26: =IFERROR(+AG11/AG21,0)*10000 -> 0
A28: 三、成本释放情况
A29: 动态成本对比启动会可释放： | C29: ='[3]06-项目成本支付计划'!$D$58+'[3]06-项目成本支付计划'!$D$83-[1]动态成本!F10 -> 4010
A31: 四、最新利润预测
A32: 指标 | B32: 启动会整体 | C32: 预计整体 | D32: 截至25年 | E32: 26年 | F32: 27年 | G32: 28年 | H32: 29年 | I32: 30年 | J32: 31年及以后 | K32: 预计-启动会 | M32: 当前-汇报
A33: 一、营业总收入 | C33: =SUM(D33:J33) -> 386141.91 | D33: =SUM([1]附件5.恒嘉相关!D5:E5)/10000 -> 0 | E33: =SUM(E84:E87,E90:E93)/1.09 -> 0 | F33: =SUM(F84:F87,F90:F93)/1.09 -> 351803.39 | G33: =SUM(G84:G87,G90:G93)/1.09 -> 22574.784 | H33: =SUM(H84:H87,H90:H93)/1.09 -> 0 | I33: =SUM(I84:I87,I90:I93)/1.09 -> 11763.734 | J33: =SUM(J84:J87,J90:J93)/1.09 -> 0 | M33: =+C33-[4]海沧璞盛!B44 -> 7469.8092
A34: 二、营业总成本 | C34: =SUM(D34:J34) -> 266169.48 | D34: =SUM(D35,D39,D41,D44,D45,D46) -> -371.37324 | E34: =SUM(E35,E39,E41,E44,E45,E46) -> -893.97575 | F34: =SUM(F35,F39,F41,F44,F45,F46) -> 236335.05 | G34: =SUM(G35,G39,G41,G44,G45,G46) -> 18974.119 | H34: =SUM(H35,H39,H41,H44,H45,H46) -> 831.49203 | I34: =SUM(I35,I39,I41,I44,I45,I46) -> 11294.161 | J34: =SUM(J35,J39,J41,J44,J45,J46) -> 0 | M34: =+C34-[4]海沧璞盛!B45 -> -60257.619
A35: 营业成本 | C35: =SUM(D35:J35) -> 253252.5 | D35: =SUM([1]附件5.恒嘉相关!D8:E8)/10000 -> 0 | F35: {=SUMPRODUCT(F71:F73,$L$108:$L$110)+F61*$L$111+SUMPRODUCT(F77:F79,$L$114:$L$116)+F67*$L$117} -> 226685.77 | G35: {=SUMPRODUCT(G71:G73,$L$108:$L$110)+G61*$L$111+SUMPRODUCT(G77:G79,$L$114:$L$116)+G67*$L$117} -> 15583.044 | H35: {=SUMPRODUCT(H71:H73,$L$108:$L$110)+H61*$L$111+SUMPRODUCT(H77:H79,$L$114:$L$116)+H67*$L$117} -> 0 | I35: {=SUMPRODUCT(I71:I73,$L$108:$L$110)+I61*$L$111+SUMPRODUCT(I77:I79,$L$114:$L$116)+I67*$L$117} -> 10983.688 | J35: {=SUMPRODUCT(J71:J73,$L$108:$L$110)+J61*$L$111+SUMPRODUCT(J77:J79,$L$114:$L$116)+J67*$L$117} -> 0 | M35: =+C35-[4]海沧璞盛!B46 -> -57180.178
A36: 其中：土地成本 | C36: =SUM(D36:J36) -> 0 | M36: =+C36-[4]海沧璞盛!B47 -> 0
A37: 建安成本 | C37: =SUM(D37:J37) -> 0 | M37: =+C37-[4]海沧璞盛!B48 -> 0
A38: 建设期财务费用 | C38: =SUM(D38:J38) -> 0 | M38: =+C38-[4]海沧璞盛!B49 -> 0
A39: 税金及附加 | C39: =SUM(D39:J39) -> 1632.828 | D39: =+SUM([1]附件5.恒嘉相关!D9:E9)/10000 -> 242.71709 | F39: =+F33*3%*12% -> 1266.4922 | G39: =+G33*3%*12% -> 81.269224 | H39: =+H33*3%*12% -> 0 | I39: =+I33*3%*12% -> 42.349442 | J39: =+J33*3%*12% -> 0 | M39: =+C39-[4]海沧璞盛!B50 -> 339.43386
A40: 其中：土增税 | C40: =SUM(D40:J40) -> 0 | M40: =+C40-[4]海沧璞盛!B51 -> 0
A41: 销售费用 | C41: =SUM(D41:J41) -> 14049.967 | D41: =SUM([1]附件5.恒嘉相关!D10:E10)/10000 -> 1694.2074 | E41: =+[1]附件5.恒嘉相关!C80 -> 590.45922 | F41: =SUM(F42:F43) -> 9017.9373 | G41: =SUM(G42:G43) -> 2479.2397 | H41: =SUM(H42:H43) -> 0 | I41: =SUM(I42:I43) -> 268.12369 | J41: =SUM(J42:J43) -> 0 | L41: =+C41/(C33*1.09) -> 0.033381195 | M41: =+C41-[4]海沧璞盛!B52 -> 1692.6351
A42: 其中：渠道费用 | C42: =SUM(D42:J42) -> 8801.0997 | F42: =+F33*[1]附件5.恒嘉相关!$B$112 -> 8018.4425 | G42: =+G33*[1]附件5.恒嘉相关!$B$112 -> 514.53345 | H42: =+H33*[1]附件5.恒嘉相关!$B$112 -> 0 | I42: =+I33*[1]附件5.恒嘉相关!$B$112 -> 268.12369 | J42: =+J33*[1]附件5.恒嘉相关!$B$112 -> 0 | M42: =+C42-[4]海沧璞盛!B53 -> 8801.0997
A43: 其他费用 | C43: =SUM(D43:J43) -> 2964.201 | F43: =+[1]附件5.恒嘉相关!D113 -> 999.49474 | G43: =+[1]附件5.恒嘉相关!E113 -> 1964.7062 | M43: =+C43-[4]海沧璞盛!B54 -> 2964.201
A44: 研发费用 | C44: =SUM(D44:J44) -> 0 | M44: =+C44-[4]海沧璞盛!B55 -> 0
A45: 管理费用 | C45: =SUM(D45:J45) -> 2509.836 | D45: =SUM([1]附件5.恒嘉相关!D11:E11)/10000 -> 18.083733 | F45: =+[1]附件5.恒嘉相关!C81 -> 829.69383 | G45: =+[1]附件5.恒嘉相关!D81 -> 830.56643 | H45: =+[1]附件5.恒嘉相关!E81 -> 831.49203 | L45: =+C45/C33/1.09 -> 0.0059630975 | M45: =+C45-[4]海沧璞盛!B56 -> -2533.973
A46: 财务费用 | C46: =SUM(D46:J46) -> -5275.6541 | D46: =SUM([1]附件5.恒嘉相关!D13:E13)/10000 -> -2326.3815 | E46: =SUM([5]Sheet5!$BJ$47:$BU$47) -> -1484.435 | F46: =SUM([5]Sheet5!$BV$47:$CG$47) -> -1464.8377 | G46: =SUM([5]Sheet5!$CH$47:$CS$47) -> 0 | H46: 0 | I46: 0 | M46: =+C46-[4]海沧璞盛!B57 -> -2575.5364
A47: 加：其他收益 | C47: =SUM(D47:J47) -> 0 | M47: =+C47-[4]海沧璞盛!B58 -> 0
A48: 资产减值损失 | C48: =SUM(D48:J48) -> 0 | M48: =+C48-[4]海沧璞盛!B59 -> 0
A49: 营业利润 | C49: =SUM(D49:J49) -> 119972.43 | D49: =+D33-D34+D47-D48 -> 371.37324 | E49: =+E33-E34+E47-E48 -> 893.97575 | F49: =+F33-F34+F47-F48 -> 115468.34 | G49: =+G33-G34+G47-G48 -> 3600.6656 | H49: =+H33-H34+H47-H48 -> -831.49203 | I49: =+I33-I34+I47-I48 -> 469.57266 | J49: =+J33-J34+J47-J48 -> 0 | M49: =+C49-[4]海沧璞盛!B60 -> 67727.428
A50: 加：营业外收入 | C50: =SUM(D50:J50) -> 64.403606 | D50: =SUM([1]附件5.恒嘉相关!D28:E28)/10000 -> 64.403606 | M50: =+C50-[4]海沧璞盛!B61 -> 64.403606
A51: 减：营业外支出 | C51: =SUM(D51:J51) -> 0 | D51: =+SUM([1]附件5.恒嘉相关!D30:E30)/10000 -> 0 | M51: =+C51-[4]海沧璞盛!B62 -> 0
A52: 三、利润总额 | C52: =SUM(D52:J52) -> 120036.83 | D52: =+D49+D50-D51 -> 435.77684 | E52: =+E49+E50-E51 -> 893.97575 | F52: =+F49+F50-F51 -> 115468.34 | G52: =+G49+G50-G51 -> 3600.6656 | H52: =+H49+H50-H51 -> -831.49203 | I52: =+I49+I50-I51 -> 469.57266 | J52: =+J49+J50-J51 -> 0 | M52: =+C52-[4]海沧璞盛!B63 -> 67791.832
A53: 减：所得税费用 | C53: =SUM(D53:J53) -> 29676.771 | F53: =+F52*0.25 -> 28867.084 | G53: =+G52*0.25 -> 900.16639 | H53: =+H52*0.25 -> -207.87301 | I53: =+I52*0.25 -> 117.39316 | M53: =+C53-[4]海沧璞盛!B64 -> 16615.52
A54: 四、净利润 | C54: =SUM(D54:J54) -> 90360.064 | D54: =+D52-D53 -> 435.77684 | E54: =+E52-E53 -> 893.97575 | F54: =+F52-F53 -> 86601.252 | G54: =+G52-G53 -> 2700.4992 | H54: =+H52-H53 -> -623.61902 | I54: =+I52-I53 -> 352.17949 | J54: =+J52-J53 -> 0 | M54: =+C54-[4]海沧璞盛!B65 -> 51176.312
A56: 套数
A57: 结转套数明细（一期） | D57: 合计 | E57: 2026年 | F57: 2027年 | G57: 2028年 | H57: 2029年 | I57: 2030年 | J57: 31年及以后 | L57: 规划可售 | M57: 无销售计划 | N57: 车均面积
A58: 住宅 | B58: 精装 | C58: 普通住宅 | D58: =SUM(E58:J58) -> 660 | F58: =(SUM(H18,Q18,T18)-E58)*0.95 -> 627 | G58: =SUM(H18,Q18,T18,W18)-SUM(E58:F58) -> 33 | H58: =SUM(H18,Q18,T18,W18,Z18)-SUM(E58:G58) -> 0 | I58: =SUM(H18,Q18,T18,W18,Z18,AC18)-SUM(E58:H58) -> 0 | J58: =E18-SUM(E58:I58) -> 0 | K58: =SUM(D58:D61)-SUM(E18:E21) -> 0
A59: 住宅 | B59: 精装 | C59: 非普通住宅 | D59: =SUM(E59:J59) -> 168 | F59: =(SUM(H19,Q19,T19)-E59)*0.95 -> 159.6 | G59: =SUM(H19,Q19,T19,W19)-SUM(E59:F59) -> 8.4 | H59: =SUM(H19,Q19,T19,W19,Z19)-SUM(E59:G59) -> 0 | I59: =SUM(H19,Q19,T19,W19,Z19,AC19)-SUM(E59:H59) -> 0 | J59: =E19-SUM(E59:I59) -> 0
A60: 商办 | B60: 毛坯 | C60: 非普通住宅 | D60: =SUM(E60:J60) -> 44 | F60: =(SUM(H20,Q20,T20)-E60)*0.95 -> 0 | G60: =SUM(H20,Q20,T20,W20)-SUM(E60:F60) -> 0 | H60: =SUM(H20,Q20,T20,W20,Z20)-SUM(E60:G60) -> 0 | I60: =SUM(H20,Q20,T20,W20,Z20,AC20)-SUM(E60:H60) -> 44 | J60: =E20-SUM(E60:I60) -> 0
A61: 车位 | B61: 毛坯 | C61: 非普通住宅 | D61: =SUM(E61:J61) -> 942 | F61: =(SUM(H21,Q21,T21)-E61)*0.95 -> 274.55 | G61: =SUM(H21,Q21,T21,W21)-SUM(E61:F61) -> 286.45 | H61: =SUM(H21,Q21,T21,W21,Z21)-SUM(E61:G61) -> 0 | I61: =SUM(H21,Q21,T21,W21,Z21,AC21)-SUM(E61:H61) -> 381 | J61: =E21-SUM(E61:I61) -> 0 | L61: =+'[3]05-1销售计划(一期)'!$G$29 -> 942 | M61: =+L61-D61 -> 0 | N61: =+'[3]02-规划输入'!$G$94 -> 31.480892
C62: 0.95
A63: 结转套数明细（二期）
A64: 住宅 | B64: 精装 | C64: 普通住宅 | D64: =SUM(E64:J64) -> 227 | F64: =(SUM(I18,R18,U18)-E64)*0.95 -> 215.65 | G64: =SUM(I18,R18,U18,X18)-SUM(E64:F64) -> 11.35 | H64: =SUM(I18,R18,U18,X18,AA18)-SUM(E64:G64) -> 0 | I64: =SUM(I18,R18,U18,X18,AA18,AD18)-SUM(E64:H64) -> 0 | J64: =+F18-SUM(E64:I64) -> 0 | K64: =SUM(D64:D67)-SUM(F18:F21) -> 0
A65: 住宅 | B65: 精装 | C65: 非普通住宅 | D65: =SUM(E65:J65) -> 0 | F65: =(SUM(I19,R19,U19)-E65)*0.95 -> 0 | G65: =SUM(I19,R19,U19,X19)-SUM(E65:F65) -> 0 | H65: =SUM(I19,R19,U19,X19,AA19)-SUM(E65:G65) -> 0 | I65: =SUM(I19,R19,U19,X19,AA19,AD19)-SUM(E65:H65) -> 0 | J65: =+F19-SUM(E65:I65) -> 0
A66: 商办 | B66: 毛坯 | C66: 非普通住宅 | D66: =SUM(E66:J66) -> 7 | F66: =(SUM(I20,R20,U20)-E66)*0.95 -> 0 | G66: =SUM(I20,R20,U20,X20)-SUM(E66:F66) -> 0 | H66: =SUM(I20,R20,U20,X20,AA20)-SUM(E66:G66) -> 0 | I66: =SUM(I20,R20,U20,X20,AA20,AD20)-SUM(E66:H66) -> 7 | J66: =+F20-SUM(E66:I66) -> 0
A67: 车位 | B67: 毛坯 | C67: 非普通住宅 | D67: =SUM(E67:J67) -> 148 | F67: =(SUM(I21,R21,U21)-E67)*0.95 -> 84.55 | G67: =SUM(I21,R21,U21,X21)-SUM(E67:F67) -> 4.45 | H67: =SUM(I21,R21,U21,X21,AA21)-SUM(E67:G67) -> 0 | I67: =SUM(I21,R21,U21,X21,AA21,AD21)-SUM(E67:H67) -> 59 | J67: =+F21-SUM(E67:I67) -> 0 | L67: =+'[3]05-2销售计划(二期)'!$G$29 -> 148 | M67: =+L67-D67 -> 0 | N67: =+'[3]02-规划输入'!$H$94 -> 45.570946
A69: 面积
A70: 结转面积明细（一期） | D70: 合计 | E70: 2026年 | F70: 2027年 | G70: 2028年 | H70: 2029年 | I70: 2030年 | J70: 31年及以后
A71: 住宅 | B71: 精装 | C71: 普通住宅 | D71: =SUM(E71:J71) -> 67535.43 | F71: =(SUM(H13,Q13,T13)*10000-E71)*0.95 -> 64158.658 | G71: =SUM(H13,Q13,T13,W13)*10000-SUM(E71:F71) -> 3376.7715 | H71: =SUM(H13,Q13,T13,W13,Z13)*10000-SUM(E71:G71) -> 0 | I71: =SUM(H13,Q13,T13,W13,Z13,AC13)*10000-SUM(E71:H71) -> 0 | J71: =E13*10000-SUM(E71:I71) -> 0 | K71: =SUM(D71:D74)-SUM(E13:E16)*10000 -> 0
A72: 住宅 | B72: 精装 | C72: 非普通住宅 | D72: =SUM(E72:J72) -> 28895.46 | F72: =(SUM(H14,Q14,T14)*10000-E72)*0.95 -> 27450.687 | G72: =SUM(H14,Q14,T14,W14)*10000-SUM(E72:F72) -> 1444.773 | H72: =SUM(H14,Q14,T14,W14,Z14)*10000-SUM(E72:G72) -> 0 | I72: =SUM(H14,Q14,T14,W14,Z14,AC14)*10000-SUM(E72:H72) -> 0 | J72: =E14*10000-SUM(E72:I72) -> 0
A73: 商办 | B73: 毛坯 | C73: 非普通住宅 | D73: =SUM(E73:J73) -> 2094.23 | F73: =(SUM(H15,Q15,T15)*10000-E73)*0.95 -> 0 | G73: =SUM(H15,Q15,T15,W15)*10000-SUM(E73:F73) -> 0 | H73: =SUM(H15,Q15,T15,W15,Z15)*10000-SUM(E73:G73) -> 0 | I73: =SUM(H15,Q15,T15,W15,Z15,AC15)*10000-SUM(E73:H73) -> 2094.23 | J73: =E15*10000-SUM(E73:I73) -> 0
A74: 车位 | B74: 毛坯 | C74: 非普通住宅 | D74: =SUM(E74:J74) -> 30330.58 | F74: =(SUM(H16,Q16,T16)*10000-E74)*0.95 -> 9225.165 | G74: =SUM(H16,Q16,T16,W16)*10000-SUM(E74:F74) -> 9111.195 | H74: =SUM(H16,Q16,T16,W16,Z16)*10000-SUM(E74:G74) -> 0 | I74: =SUM(H16,Q16,T16,W16,Z16,AC16)*10000-SUM(E74:H74) -> 11994.22 | J74: =E16*10000-SUM(E74:I74) -> 0
A76: 结转面积明细（二期）
A77: 住宅 | B77: 精装 | C77: 普通住宅 | D77: =SUM(E77:J77) -> 0 | K77: ①绿框公式里面第一个sum公式后面的式子往右移动1列；②被减数sum公式往下移动6行
A78: 住宅 | B78: 精装 | C78: 非普通住宅 | D78: =SUM(E78:J78) -> 0
A79: 商办 | B79: 毛坯 | C79: 非普通住宅 | D79: =SUM(E79:J79) -> 0
A80: 车位 | B80: 毛坯 | C80: 非普通住宅 | D80: =SUM(E80:J80) -> 0
A82: 货值
A83: 结转含税货值明细（一期） | D83: 合计 | E83: 2026年 | F83: 2027年 | G83: 2028年 | H83: 2029年 | I83: 2030年 | J83: 31年及以后
A84: 住宅 | B84: 精装 | C84: 普通住宅 | D84: =SUM(E84:J84) -> 224412.13 | F84: =(SUM(H8,Q8,T8)*10000-E84)*0.95 -> 213191.52 | G84: =SUM(H8,Q8,T8,W8)*10000-SUM(E84:F84) -> 11220.606 | H84: =SUM(H8,Q8,T8,W8,Z8)*10000-SUM(E84:G84) -> 0 | I84: =SUM(H8,Q8,T8,W8,Z8,AC8)*10000-SUM(E84:H84) -> 0 | J84: =E8*10000-SUM(E84:I84) -> 0 | K84: =SUM(D84:D87)-SUM(E8:E11)*10000 -> 0
A85: 住宅 | B85: 精装 | C85: 非普通住宅 | D85: =SUM(E85:J85) -> 89907.291 | F85: =(SUM(H9,Q9,T9)*10000-E85)*0.95 -> 85411.927 | G85: =SUM(H9,Q9,T9,W9)*10000-SUM(E85:F85) -> 4495.3646 | H85: =SUM(H9,Q9,T9,W9,Z9)*10000-SUM(E85:G85) -> 0 | I85: =SUM(H9,Q9,T9,W9,Z9,AC9)*10000-SUM(E85:H85) -> 0 | J85: =E9*10000-SUM(E85:I85) -> 0
A86: 商办 | B86: 毛坯 | C86: 非普通住宅 | D86: =SUM(E86:J86) -> 6282.69 | F86: =(SUM(H10,Q10,T10)*10000-E86)*0.95 -> 0 | G86: =SUM(H10,Q10,T10,W10)*10000-SUM(E86:F86) -> 0 | H86: =SUM(H10,Q10,T10,W10,Z10)*10000-SUM(E86:G86) -> 0 | I86: =SUM(H10,Q10,T10,W10,Z10,AC10)*10000-SUM(E86:H86) -> 6282.69 | J86: =E10*10000-SUM(E86:I86) -> 0
A87: 车位 | B87: 毛坯 | C87: 非普通住宅 | D87: =SUM(E87:J87) -> 14932 | F87: =(SUM(H11,Q11,T11)*10000-E87)*0.95 -> 5277.1455 | G87: =SUM(H11,Q11,T11,W11)*10000-SUM(E87:F87) -> 4701.8545 | H87: =SUM(H11,Q11,T11,W11,Z11)*10000-SUM(E87:G87) -> 0 | I87: =SUM(H11,Q11,T11,W11,Z11,AC11)*10000-SUM(E87:H87) -> 4953 | J87: =E11*10000-SUM(E87:I87) -> 0
A89: 结转含税货值明细（二期）
A90: 住宅 | B90: 精装 | C90: 普通住宅 | D90: =SUM(E90:J90) -> 81962.791 | F90: =(SUM(I8,R8,U8)*10000-E90)*0.95 -> 77864.651 | G90: =SUM(I8,R8,U8,X8)*10000-SUM(E90:F90) -> 4098.1395 | H90: =SUM(I8,R8,U8,X8,AA8)*10000-SUM(E90:G90) -> 0 | I90: =SUM(I8,R8,U8,X8,AA8,AD8)*10000-SUM(E90:H90) -> 0 | J90: =F8*10000-SUM(E90:I90) -> 0 | K90: =SUM(D90:D93)-SUM(F8:F11)*10000 -> 0
A91: 住宅 | B91: 精装 | C91: 非普通住宅 | D91: =SUM(E91:J91) -> 0 | F91: =(SUM(I9,R9,U9)*10000-E91)*0.95 -> 0 | G91: =SUM(I9,R9,U9,X9)*10000-SUM(E91:F91) -> 0 | H91: =SUM(I9,R9,U9,X9,AA9)*10000-SUM(E91:G91) -> 0 | I91: =SUM(I9,R9,U9,X9,AA9,AD9)*10000-SUM(E91:H91) -> 0 | J91: =F9*10000-SUM(E91:I91) -> 0
A92: 商办 | B92: 毛坯 | C92: 非普通住宅 | D92: =SUM(E92:J92) -> 819.78 | F92: =(SUM(I10,R10,U10)*10000-E92)*0.95 -> 0 | G92: =SUM(I10,R10,U10,X10)*10000-SUM(E92:F92) -> 0 | H92: =SUM(I10,R10,U10,X10,AA10)*10000-SUM(E92:G92) -> 0 | I92: =SUM(I10,R10,U10,X10,AA10,AD10)*10000-SUM(E92:H92) -> 819.78 | J92: =F10*10000-SUM(E92:I92) -> 0
A93: 车位 | B93: 毛坯 | C93: 非普通住宅 | D93: =SUM(E93:J93) -> 2578 | F93: =(SUM(I11,R11,U11)*10000-E93)*0.95 -> 1720.45 | G93: =SUM(I11,R11,U11,X11)*10000-SUM(E93:F93) -> 90.55 | H93: =SUM(I11,R11,U11,X11,AA11)*10000-SUM(E93:G93) -> 0 | I93: =SUM(I11,R11,U11,X11,AA11,AD11)*10000-SUM(E93:H93) -> 767 | J93: =F11*10000-SUM(E93:I93) -> 0
A94: 单价
A95: 结转单价明细（一期） | D95: 合计 | E95: 2026年 | F95: 2027年 | G95: 2028年 | H95: 2029年 | I95: 2030年 | J95: 31年及以后
A96: 住宅 | B96: 精装 | C96: 普通住宅 | D96: =IFERROR(+D84/D71,0) -> 3.32288 | E96: =IFERROR(+E84/E71,0) -> 0 | F96: =IFERROR(+F84/F71,0) -> 3.32288 | G96: =IFERROR(+G84/G71,0) -> 3.32288 | H96: =IFERROR(+H84/H71,0) -> 0 | I96: =IFERROR(+I84/I71,0) -> 0 | J96: =IFERROR(+J84/J71,0) -> 0 | K96: =+D96-E23 -> 0
A97: 住宅 | B97: 精装 | C97: 非普通住宅 | D97: =IFERROR(+D85/D72,0) -> 3.1114677 | E97: =IFERROR(+E85/E72,0) -> 0 | F97: =IFERROR(+F85/F72,0) -> 3.1114677 | G97: =IFERROR(+G85/G72,0) -> 3.1114677 | H97: =IFERROR(+H85/H72,0) -> 0 | I97: =IFERROR(+I85/I72,0) -> 0 | J97: =IFERROR(+J85/J72,0) -> 0 | K97: =+D97-E24 -> 0
A98: 商办 | B98: 毛坯 | C98: 非普通住宅 | D98: =IFERROR(+D86/D73,0) -> 3 | E98: =IFERROR(+E86/E73,0) -> 0 | F98: =IFERROR(+F86/F73,0) -> 0 | G98: =IFERROR(+G86/G73,0) -> 0 | H98: =IFERROR(+H86/H73,0) -> 0 | I98: =IFERROR(+I86/I73,0) -> 3 | J98: =IFERROR(+J86/J73,0) -> 0 | K98: =+D98-E25 -> 0
A99: 车位 | B99: 毛坯 | C99: 非普通住宅 | D99: =IFERROR(+D87/D61,0) -> 15.85138 | E99: =IFERROR(+E87/E61,0) -> 0 | F99: =IFERROR(+F87/F61,0) -> 19.221073 | G99: =IFERROR(+G87/G61,0) -> 16.414224 | H99: =IFERROR(+H87/H61,0) -> 0 | I99: =IFERROR(+I87/I61,0) -> 13 | J99: =IFERROR(+J87/J61,0) -> 0 | K99: =+D99-E26 -> 0
A101: 结转单价明细（二期）
A102: 住宅 | B102: 精装 | C102: 普通住宅 | D102: =IFERROR(+D90/D77,0) -> 0 | E102: =IFERROR(+E90/E77,0) -> 0 | F102: =IFERROR(+F90/F77,0) -> 0 | G102: =IFERROR(+G90/G77,0) -> 0 | H102: =IFERROR(+H90/H77,0) -> 0 | I102: =IFERROR(+I90/I77,0) -> 0 | J102: =IFERROR(+J90/J77,0) -> 0 | K102: =+D102-F23 -> -3.4298877
A103: 住宅 | B103: 精装 | C103: 非普通住宅 | D103: =IFERROR(+D91/D78,0) -> 0 | E103: =IFERROR(+E91/E78,0) -> 0 | F103: =IFERROR(+F91/F78,0) -> 0 | G103: =IFERROR(+G91/G78,0) -> 0 | H103: =IFERROR(+H91/H78,0) -> 0 | I103: =IFERROR(+I91/I78,0) -> 0 | J103: =IFERROR(+J91/J78,0) -> 0 | K103: =+D103-F24 -> 0
A104: 商办 | B104: 毛坯 | C104: 非普通住宅 | D104: =IFERROR(+D92/D79,0) -> 0 | E104: =IFERROR(+E92/E79,0) -> 0 | F104: =IFERROR(+F92/F79,0) -> 0 | G104: =IFERROR(+G92/G79,0) -> 0 | H104: =IFERROR(+H92/H79,0) -> 0 | I104: =IFERROR(+I92/I79,0) -> 0 | J104: =IFERROR(+J92/J79,0) -> 0 | K104: =+D104-F25 -> -3
A105: 车位 | B105: 毛坯 | C105: 非普通住宅 | D105: =IFERROR(+D93/D67,0) -> 17.418919 | E105: =IFERROR(+E93/E67,0) -> 0 | F105: =IFERROR(+F93/F67,0) -> 20.348315 | G105: =IFERROR(+G93/G67,0) -> 20.348315 | H105: =IFERROR(+H93/H67,0) -> 0 | I105: =IFERROR(+I93/I67,0) -> 13 | J105: =IFERROR(+J93/J67,0) -> 0 | K105: =+D105-F26 -> 0
A106: 单方
A107: 结转单方明细（一期） | D107: 合计 | F107: 资本化利息结余 | H107: 建造成本结余 | J107: 资本化管费增项 | L107: 调整后合计
A108: 住宅 | B108: 精装 | C108: 普通住宅 | D108: =+'[3]06-2成本分摊'!$Y$6 -> 2.4676132 | F108: =+B121/SUM(D71:D74,D77:D80) -> -0.0438405 | H108: =-C29/1.09/SUM(D71:D74,D77:D80) -> -0.028550534 | J108: =+B123/SUM(D71:D74,D77:D80) -> 0.011475857 | L108: =+D108+F108+H108+J108 -> 2.406698
...

Sheet Sheet1
A1: 面积
A2: 结转面积明细（一期） | D2: 合计 | E2: 2026年 | F2: 2027年 | G2: 2028年 | H2: 2029年 | I2: 2030年
A3: 住宅 | B3: 精装 | C3: 普通住宅 | E3: =(SUM(H13,P13,S13)*10000-E71)*0.95 -> 0 | F3: =SUM(H13,P13,S13,V13)*10000-SUM(E71:F71) -> 0 | G3: =SUM(H13,P13,S13,V13,Y13)*10000-SUM(E71:G71) -> 0 | H3: =SUM(H13,P13,S13,V13,Y13,AB13)*10000-SUM(E71:H71) -> 0 | I3: =E13*10000-SUM(E71:I71) -> 0
A4: 住宅 | B4: 精装 | C4: 非普通住宅
A5: 商办 | B5: 毛坯 | C5: 非普通住宅
A6: 车位 | B6: 毛坯 | C6: 非普通住宅
A8: 结转面积明细（二期）
A9: 住宅 | B9: 精装 | C9: 普通住宅 | E9: =(SUM(I13,R13,U13)*10000-E77)*0.95 -> 0 | F9: =SUM(I13,R13,U13,X13)*10000-SUM(E77:F77) -> 0 | G9: =SUM(I13,R13,U13,X13,AA13)*10000-SUM(E77:G77) -> 0 | H9: =SUM(I13,R13,U13,X13,AA13,AD13)*10000-SUM(E77:H77) -> 0 | I9: =F13*10000-SUM(E77:I77) -> 0
A10: 住宅 | B10: 精装 | C10: 非普通住宅
A11: 商办 | B11: 毛坯 | C11: 非普通住宅
A12: 车位 | B12: 毛坯 | C12: 非普通住宅
